{"id":0,"category":"选择题","question":"某股份制银行2019年已完成“两增”目标且普惠贷款占比超10%，其在2020年的最低考核要求是什么？","content":"   A. 必须继续保持30%以上的增速  \n   B. 只需维持贷款余额和户数不低于年初水平  \n   C. 需额外增加信用贷款比例  \n   D. 暂停当年的小微企业贷款任务  "}
{"id":1,"category":"选择题","question":"以下哪些属于柜台债券市场的合法交易品种？","content":"   A. 现券买卖  \n   B. 股指期货  \n   C. 质押式回购  \n   D. 买断式回购  "}
{"id":2,"category":"选择题","question":"境外机构境内发行债券的登记手续通常由谁负责办理？","content":"   A. 开户银行\n   B. 境内主承销商\n   C. 当地税务机关\n   D. 债券认购方"}
{"id":3,"category":"选择题","question":"债券市场资金专户允许的资金支出包括哪些？","content":"   A) 支付债券交易价款  \n   B) 购买海外股票资产  \n   C) 投资收益汇至母公司账户  \n   D) 房地产项目定向投资  "}
{"id":4,"category":"选择题","question":"质押贷款期限内允许的行为有哪些？","content":"   A. 借款人申请展期  \n   B. 存款行主动变更存单利率  \n   C. 出质人自行办理存单挂失  \n   D. 继承人办理存款过户手续  "}
{"id":5,"category":"问答题","question":"若发现某金融机构在回购交易中多次突破质押比例上限，监管当局可采取哪些处置手段？","content":null}
{"id":6,"category":"选择题","question":"存单质押贷款的最长期限取决于什么？","content":"   A. 主合同约定的还款计划  \n   B. 质押存单中最临近的到期日  \n   C. 贷款银行的信贷规模限制  \n   D. 监管部门设定的行业标准  "}
{"id":7,"category":"选择题","question":"境外证券借贷业务担保物最低覆盖率应为？","content":"   A. 100%  \n   B. 101%  \n   C. 102%  \n   D. 105%  "}
{"id":8,"category":"选择题","question":"保险资金参与股指期货交易，哪些行为是被绝对禁止的？","content":"   A. 合并轧差计算买卖合约价值  \n   B. 用于对冲已有股票的下跌风险  \n   C. 持仓超过资产组合净值100%  \n   D. 交易员薪酬与短期交易盈利挂钩  "}
{"id":9,"category":"选择题","question":"境外机构在中国境内发行人民币债券的资金账户管理要求不包括哪一项？","content":"   A. 专户存放募集资金  \n   B. 按活期利率计息  \n   C. 允许临时周转挪用  \n   D. 限定于申报用途使用  "}
{"id":10,"category":"选择题","question":"村镇银行年度计划须明确哪些关键信息？","content":"   A. 具体设立地点清单  \n   B. 当地金融市场饱和度分析  \n   C. 人员招聘方案模板  \n   D. 挂钩政策实施方案  "}
{"id":11,"category":"选择题","question":"在面签阶段仅有借款人单方面签字的情况下，银行若要继续签约必须具备什么前提？","content":"   A. 上级领导特别批准  \n   B. 担保人同步签署协议  \n   C. 确认无法律瑕疵且收益覆盖风险  \n   D. 地方政府出具推荐函  "}
{"id":12,"category":"选择题","question":"中国人民银行动态调整实物备付比例的决策因素不包括以下哪项？","content":"   A) 黄金市场价格整体走势  \n   B) 账户黄金业务总体规模  \n   C) 单日国际金价波动幅度  \n   D) 银行风控体系有效性评估  "}
{"id":13,"category":"选择题","question":"大额存单的利率确定依据是什么？","content":"   A. 央行统一指导价  \n   B. 市场竞价拍卖结果  \n   C. Shibor浮动基准或固定年化收益率  \n   D. 同期国债收益率上浮一定比例  "}
{"id":14,"category":"选择题","question":"外资银行可以在几家商业银行开设结售汇人民币专户？","content":"   A. 任意多家  \n   B. 仅限总行所在省分行的1家  \n   C. 根据业务需要选定1家  \n   D. 不允许在商业银行开户  "}
{"id":15,"category":"选择题","question":"银行保险机构案件中谁承担最终责任？","content":"   A. 监事会  \n   B. 高级管理层  \n   C. 董（理）事会  \n   D. 内部审计部门  "}
{"id":16,"category":"选择题","question":"全国性银行内部转移定价对小微信贷的最低优惠幅度是多少？","content":"   A) 20基点  \n   B) 30基点  \n   C) 50基点  \n   D) 100基点  "}
{"id":17,"category":"选择题","question":"在国库资金经收支付服务模式二中，负责发起TIPS银行端查询缴税业务的主体是？","content":"   A. 商业银行  \n   B. 清算机构  \n   C. 非银行支付机构  \n   D. 缴款人本人  "}
{"id":18,"category":"选择题","question":"境外专业子公司设立项目公司开展业务后应向哪个机构定期报告？","content":"   A) 海关总署  \n   B) 商务部外资司  \n   C) 属地银监局  \n   D) 外汇管理局  "}
{"id":19,"category":"选择题","question":"单位代理个人办理银行卡时，下列哪个行为是被明令禁止的？","content":"   A. 提交真实的申请人资料  \n   B. 为非本单位员工代理办卡  \n   C. 在确认身份前限制卡片功能  \n   D. 提前签署书面代理协议  "}