{"id": 510, "answer": ["B"]}
{"id": 507, "answer": ["D"]}
{"id": 513, "answer": ["C"]}
{"id": 505, "answer": ["C"]}
{"id": 514, "answer": ["B"]}
{"id": 506, "answer": ["B"]}
{"id": 501, "answer": ["C"]}
{"id": 522, "answer": ["A", "D"]}
{"id": 519, "answer": ["B"]}
{"id": 508, "answer": ["A"]}
{"id": 527, "answer": ["B"]}
{"id": 523, "answer": "可通过保险公司提供的电话、互联网等官方渠道查询已购人身保险的详细保单信息，内容包括产品名称、条款、保单号、投保人及被保险人信息、保险费、交费方式、保险金额、保险期间、保险责任、责任免除、等待期、保单生效日、销售渠道等。具体操作需联系保险公司客服或登录其官方平台进行查询。"}
{"id": 503, "answer": "突发重大法律诉讼时，应履行以下合规程序：（1）及时向监管部门报告重大诉讼事件（如涉案金额超过净资产10%的纠纷）；（2）遵循法律程序，如论证诉讼可行性并依法采取追偿措施；（3）披露法律诉讼进度及影响（如资产支持证券需披露诉讼进展）；（4）评估风险并制定应对措施，确保金融秩序稳定；（5）启动应急预案，保障金融服务连续性。依据来源包括段落2、5、4、3及1。"}
{"id": 529, "answer": "应立即停止向无证机构开放支付业务接口，依据《中国人民银行关于规范支付创新业务的通知》（银发2017281号）要求，建立统一接口管理制度，严格接入单位资质审核，防止接口被用于违法违规用途；同时向中国人民银行分支机构报告违规行为，配合依法处置无证机构（依据段落2、段落3、段落5）。"}
{"id": 518, "answer": ["B"]}
{"id": 511, "answer": ["A", "B"]}
{"id": 515, "answer": ["D"]}
{"id": 525, "answer": ["A"]}
{"id": 517, "answer": "应启动债券系统应急处理功能，具体包括中央结算公司根据授权启用应急功能或成员行按应急处置方案操作。"}
{"id": 504, "answer": ["C"]}
{"id": 520, "answer": ["A"]}
{"id": 500, "answer": ["C"]}
{"id": 524, "answer": ["B"]}
{"id": 528, "answer": "同业存款业务的主要分类依据是期限、业务关系和用途。"}
{"id": 502, "answer": ["A", "C"]}
{"id": 509, "answer": ["B", "D"]}
{"id": 531, "answer": ["A", "C"]}
{"id": 530, "answer": "新旧绿色债券目录过渡期的三项衔接规则为：（1）已存续或已核准的债券按《绿色债券支持项目目录（2015年版）》执行；（2）已申报但未核准的债券可选择适用旧目录或新目录；（3）鼓励发债主体按新目录进行信息披露。"}
{"id": 526, "answer": ["D"]}
{"id": 532, "answer": ["A"]}
{"id": 521, "answer": ["C"]}
{"id": 533, "answer": ["A", "B", "D"]}
{"id": 535, "answer": ["C"]}
{"id": 534, "answer": ["B"]}
{"id": 536, "answer": ["B"]}
{"id": 540, "answer": ["C"]}
{"id": 516, "answer": ["A", "B"]}
{"id": 512, "answer": "当质押存单期限早于贷款期限时，贷款人应确保贷款期限不超过存单到期日（依据段落1第八条）。若贷款期限已超出存单期限，贷款人需通过展期（段落1第十条）或提前还款等方式调整，累计贷款期限不得超过存单到期日。若存单期限早于贷款期限（即贷款期限更长），则违反规定，贷款人应调整贷款期限或采取其他合法措施确保债权实现。"}
{"id": 542, "answer": ["C"]}
{"id": 545, "answer": ["C"]}
{"id": 538, "answer": "银保监会主要通过以下方式强化事中事后监管：一是加强对登记机构的业务指导，完善其流程、系统及人员管理，并强化风险监测职责；二是压实保险资产管理机构主体责任，要求其提升登记质量与信息披露规范性；三是强化日常监管，将登记情况纳入监管评级，并对不力机构采取监管措施；四是落实“放管结合”，明确监管职责，防止监管真空，确保审批与监管权责统一。"}
{"id": 544, "answer": ["B"]}
{"id": 541, "answer": ["C"]}
{"id": 550, "answer": ["B"]}
{"id": 537, "answer": "不能办理定期存款业务。依据是《中华人民共和国临时居民身份证管理办法》规定临时身份证有效期为三个月，且未标明有效期的证件无法确认是否在有效期内，银行可能因此拒绝接受其作为实名证件。"}
{"id": 539, "answer": []}
{"id": 546, "answer": []}
{"id": 549, "answer": "本次汇率调整的核心变更内容是：银行可在规定价差幅度内自行调整当日美元挂牌价格，中国人民银行根据市场供求和篮子货币汇率变动，对人民币汇率进行管理和调节，以保持其在合理、均衡水平上的基本稳定。"}
{"id": 548, "answer": "开户单位与中国人民银行账务余额核对不一致时，应逐笔勾对发生额查明原因，由主管确认对账结果并说明；中国人民银行事后监督部门需在当日确认结果，营业部门应与开户单位联系查清原因，双方需及时查找差异根源并妥善解决。"}
{"id": 553, "answer": ["B"]}
{"id": 547, "answer": ["C"]}
{"id": 554, "answer": ["A", "D"]}
{"id": 543, "answer": ["A"]}
{"id": 552, "answer": ["B"]}
{"id": 557, "answer": ["C"]}
{"id": 556, "answer": ["B"]}
{"id": 551, "answer": "金融机构开展买入返售业务时，标的资产应为银行承兑汇票、债券、央票等在银行间市场或证券交易所市场交易的具有合理公允价值和较高流动性的金融资产（根据段落2），且交易对手需符合穿透原则和准入管理要求，三方或以上交易对手的类似交易不得纳入买入返售业务管理（根据段落2）。同时，标的资产需与销售文件约定的投资范围保持一致（根据段落1）。"}
{"id": 555, "answer": "若银行质押债券到期未解押，将导致兑付资金被中央结算公司提存，并可能影响质押额度的正常使用。后续处理包括：1. 向人民银行申请解除提存，经审核后恢复资金划转；2. 若债务未清偿，依据银监会规定，银行需通过变卖、拍卖等方式处置质押品以清偿债务。"}
{"id": 560, "answer": ["C"]}
{"id": 563, "answer": ["A", "C"]}
{"id": 562, "answer": ["C"]}
{"id": 561, "answer": ["A"]}
{"id": 559, "answer": "机构在进行黄金衍生品交易时，应遵守以下核心法律约束：1. 符合外汇管理规定（如段落3所述外汇敞口管理及套期保值操作）；2. 遵守金融衍生品相关法律法规（如段落1提及的《中华人民共和国中国人民银行法》）；3. 履行反洗钱与反恐怖融资义务（段落1）；4. 保障金融消费者权益（段落1）；5. 接受中国人民银行及上海黄金交易所的监督管理（段落1、段落5）；6. 对黄金衍生品业务进行备案并符合金融监管部门的管理规定（段落4）；7. 建立完善的内部控制和风险管理制度（段落2）。"}
{"id": 564, "answer": ["B", "D"]}
{"id": 567, "answer": ["B"]}
{"id": 565, "answer": "金融机构在自评时提交虚假材料将引发以下监管措施：1. 监管评价结果直接认定为较低等级（如四级或D/E类）；2. 扣减评分（如5-15分）；3. 情节严重的直接认定为最低等级（如E类）；4. 通过文件、约谈等方式通报评价结果。"}
{"id": 574, "answer": "当采用担保方式发行资本补充债券时，需额外提交担保协议。"}
{"id": 566, "answer": ["C"]}
{"id": 571, "answer": ["A", "B", "C", "D"]}
{"id": 558, "answer": ["B", "D"]}
{"id": 575, "answer": ["A", "B", "C", "D"]}
{"id": 576, "answer": ["A", "B"]}
{"id": 572, "answer": "BBB级企业债券的违约风险特性表现为中等水平，受不利经济环境和经营条件影响较大，偿债能力一般，存在一定波动性。尽管其代偿能力尚可，但未来经营受不确定因素影响，可能导致盈利和偿债能力波动，约定的保障条件可能不足以完全覆盖违约风险。"}
{"id": 570, "answer": []}
{"id": 573, "answer": ["C"]}
{"id": 577, "answer": ["B"]}
{"id": 581, "answer": ["B"]}
{"id": 583, "answer": "金融机构应将已停用的旧版汇票专用章按规定销毁，并接受中国人民银行各分支行的定期检查，确保旧章不再用于票据业务。"}
{"id": 582, "answer": "小微企业划型的法定依据是《关于印发中小企业划型标准规定的通知》（工信部联企业〔2011〕300号）。"}
{"id": 578, "answer": ["A", "C", "D"]}
{"id": 568, "answer": []}
{"id": 585, "answer": "银行间债券市场中常见的债券类型包括政府债券、中央银行债券、金融债券、企业债券、公司债券、非金融企业债务融资工具以及资产支持证券等。"}
{"id": 584, "answer": ["B"]}
{"id": 580, "answer": "发现保险销售人员私自修改产品宣传资料，应首先依据《人身保险产品信息披露管理办法》追究其内部责任（如警告、罚款或解雇），并由银保监会等监管机构进行行政处罚（如罚款、责令整改）。若造成消费者损失，还需承担民事赔偿责任，情节严重的可能涉及刑事责任。"}
{"id": 569, "answer": ["B", "D"]}
{"id": 579, "answer": "代办年度额度内的个人购汇业务需遵循以下步骤：1. 代办人须为直系亲属（父母、子女、配偶）或其他符合规定的人员，需提供双方有效身份证件、授权书及直系亲属关系证明（如户口簿、结婚证等）；2. 填写《个人购汇申请书》，明确购汇用途（如因私旅游、留学等），并勾选“本人保证申报信息真实有效”；3. 银行通过个人结售汇系统录入数据并打印“结汇/购汇通知单”作为凭证；4. 确保购汇用途真实合法，不得违规借用或出借额度。依据段落2、3、4。"}
{"id": 587, "answer": "行政处罚委员会的主要职责包括：（1）审议行政处罚案件并作出决定；（2）审议案件审理指导意见及本单位涉及行政处罚的重要管理制度；（3）对下级行行政处罚委员会进行指导和监督；（4）审议本单位与行政处罚工作相关的其他重大事项。"}
{"id": 592, "answer": ["C"]}
{"id": 586, "answer": ["A", "B"]}
{"id": 588, "answer": ["B"]}
{"id": 593, "answer": ["A", "C"]}
{"id": 596, "answer": ["A"]}
{"id": 598, "answer": ["B"]}
{"id": 597, "answer": ["C"]}
{"id": 591, "answer": "个体工商户申请安装扫码收款设备需满足以下条件：1. 提供合法经营证明，如营业场所租赁协议或产权证明等辅助材料（依据段落3）；2. 确保设备符合国家技术标准，如扫码设备需具备唯一性、可重复性及符合GB18030等规范（依据段落1、段落2）。此外，需与收单机构签订条码支付受理协议，明确结算周期、手续费等条款（依据段落3）。"}
{"id": 599, "answer": ["A", "C"]}
{"id": 590, "answer": ["D"]}
{"id": 595, "answer": ["C"]}
{"id": 603, "answer": ["A", "B"]}
{"id": 606, "answer": ["B"]}
{"id": 609, "answer": ["B"]}
{"id": 602, "answer": "企业挪用流动资金贷款时，金融机构及监管机构可能采取的风控措施包括：1. 根据《中华人民共和国银行业监督管理法》实施监管处罚（段落1）；2. 停止融资支持并上报征信系统（段落3）；3. 通过法律诉讼追责（段落3）；4. 立即收回违规贷款（段落5）；5. 加强贷款用途监督，防止资金挪用（段落2）。"}
{"id": 600, "answer": ["A", "B", "C"]}
{"id": 601, "answer": ["D"]}
{"id": 607, "answer": "资金业务系统性风险防控需重点关注以下量化指标：1）交易特征指标（如单次交易金额、累计交易金额、交易频率、交易对手分布、IP/MAC地址等）；2）宏观经济与金融体系指标（如GDP增长率、CPI、利率、金融体系流动性、杠杆率、信贷增速）；3）流动性风险指标（如流动性覆盖率LCR、净稳定资金比例NSFR）；4）信用风险指标（如不良贷款率、贷款集中度）；5）系统重要性机构风险指标（如核心一级资本充足率、资本回报率）。这些指标需结合非现场监管数据（段落2-3）和交易监测数据（段落1）进行动态评估。"}
{"id": 611, "answer": ["C"]}
{"id": 608, "answer": "怀疑银行卡被盗刷时，应立即采取以下措施：1. 联系发卡银行客服或通过官方挂失电话核实身份后申请冻结账户；2. 修改银行卡交易密码，确保密码安全；3. 向公安机关报案并提供相关交易记录；4. 监控账户动态，及时发现异常交易；5. 如涉及跨境交易，可向银联或相关金融机构进一步确认。这些措施可最大限度减少损失并保障账户安全。"}
{"id": 612, "answer": ["A"]}
{"id": 613, "answer": "银行应依据银监会《节能减排授信工作指导意见》采取以下风控措施：1. 停止拨付开工前准备及建设资金（依据段落1第十三条）；2. 暂停主体工程资金拨付直至环保设施与主体工程“三同时”实现（依据段落2第十三条）；3. 项目完工后若未通过竣工环评，不得拨付运营资金（依据段落2第十三条）。操作依据为银监发200783号文件对环评审批与授信资金拨付的强制性合规要求。"}
{"id": 604, "answer": ["A", "B"]}
{"id": 615, "answer": ["A", "C"]}
{"id": 614, "answer": ["B"]}
{"id": 610, "answer": ["B"]}
{"id": 605, "answer": ["D"]}
{"id": 616, "answer": ["C"]}
{"id": 594, "answer": ["A", "B"]}
{"id": 621, "answer": ["C"]}
{"id": 617, "answer": ["A"]}
{"id": 622, "answer": ["B"]}
{"id": 619, "answer": "同业拆借中心和托管机构发现债券交易异常时，应采取以下措施：1. 及时处理异常情况；2. 向中国人民银行报告；3. 同时抄送中国银行间市场交易商协会；4. 通知中国人民银行相关省一级分支机构。这些措施依据段落1、段落2和段落4的规定。"}
{"id": 620, "answer": "外汇交易中心与上海清算所的协作机制包含以下内容：（1）建立健全银行间市场运行日常监测机制和市场风险预警指标体系；（2）建立信息和数据共享机制（涉密信息除外）；（3）定期沟通业务系统协同运行情况，评估系统效率、稳定性及业务技术风险；（4）根据业务发展需要，加强与其他相关机构的沟通配合。这些内容依据段落1、段落2、段落4的描述综合得出。"}
{"id": 623, "answer": ["A"]}
{"id": 625, "answer": "承兑人需满足以下前提条件：1. 无逾期余额且已披露当期承兑人信用信息；2. 向市场发布公告说明逾期原因；3. 公告发布后或次月不再构成承兑人逾期。同时需消除导致暂停服务的违规行为（如持续逾期或信用信息延迟披露）。"}
{"id": 624, "answer": "信托类产品的受益所有人范围包括信托的委托人、受托人、受益人以及其他对信托实施最终有效控制的自然人。根据《受益所有人信息管理办法》，需穿透至最终拥有或实际控制信托，或享有其最终收益的自然人。若自然人通过直接或间接方式最终拥有信托25%以上权益、表决权，或虽未达25%但实际享有控制权或收益权，亦属于受益所有人。"}
{"id": 626, "answer": ["C"]}
{"id": 618, "answer": ["C"]}
{"id": 627, "answer": ["B"]}
{"id": 631, "answer": ["C"]}
{"id": 630, "answer": ["C", "D"]}
{"id": 629, "answer": ["A", "C"]}
{"id": 628, "answer": "此次汇率浮动幅度扩大的政策设计通过扩大市场定价空间（如将浮动幅度由1%扩大至2%）体现市场化改革，同时通过央行的宏观审慎管理（如参考篮子货币、保持汇率基本稳定）和强化金融机构风险控制（如要求银行严格遵守监管要求）实现风险防控。这种“市场决定汇率”与“有管理的浮动汇率制度”相结合的设计，体现了市场化与风险防控的平衡。"}
{"id": 589, "answer": []}
{"id": 632, "answer": ["C"]}
{"id": 635, "answer": "申请流动资金贷款的企业需满足以下基本资质：1. 依法经市场监督管理部门或主管部门核准登记；2. 借款用途明确且合法；3. 经营活动合法合规；4. 具备持续经营能力及合法还款来源；5. 信用状况良好；6. 满足贷款人要求的其他条件。"}
{"id": 634, "answer": "信托终止后需完成信托终止登记，具体程序包括：1. 信托机构应在解除受托人责任后10个工作日内申请信托终止登记；2. 提交信托终止登记申请书、受托人出具的清算报告及法律要求的其他文件。清算报告需在信托终止后10个工作日内完成并经审计（或根据信托文件约定提交未经审计的报告）。"}
{"id": 637, "answer": ["B"]}
{"id": 641, "answer": ["B"]}
{"id": 639, "answer": "商户申请移动POS机需准备的材料通常包括营业执照、法人身份证明、行业资质证明、经营场所证明及合规经营承诺书等，且需符合特定行业范围（如航空、餐饮、物流配送等）。具体要求可能因收单银行而异，但需经银行审核批准。"}
{"id": 633, "answer": ["B"]}
{"id": 636, "answer": ["A", "B", "C"]}
{"id": 642, "answer": ["B"]}
{"id": 644, "answer": ["C"]}
{"id": 643, "answer": ["A", "C"]}
{"id": 646, "answer": ["C"]}
{"id": 648, "answer": ["B", "D"]}
{"id": 647, "answer": ["A", "B"]}
{"id": 640, "answer": ["D"]}
{"id": 645, "answer": ["B"]}
{"id": 652, "answer": ["B"]}
{"id": 654, "answer": ["B"]}
{"id": 650, "answer": ["A", "B"]}
{"id": 649, "answer": ["B"]}
{"id": 656, "answer": "在债券借贷期间，若标的债券发生派息，债券融入方需及时向债券融出方返还相应的债券利息，具体操作应依据双方签署的主协议条款执行。"}
{"id": 657, "answer": "餐厅引入扫码点餐需取得以下法定资质：1. 与具备条码支付业务许可的支付机构合作（依据段落2第四条）；2. 餐厅自身需通过实名制审核，提供合法营业执照等证明文件（依据段落1第二十四条）。此外，需遵守反洗钱及数据安全规定（段落2第六条、段落3/5）。"}
{"id": 651, "answer": "银行应通过以下方式利用政务数据改善中小微企业信用评估：1. 整合跨部门涉企信用信息（如市场监管、税务等），提升数据归集共享的广度和深度；2. 对接地方征信平台，获取中小微企业信用信息并建立优质企业信息库；3. 利用动产和权利担保统一登记系统，完善信用评估模型；4. 推动地方政府信用信息共享机制，优化融资担保和风险补偿机制；5. 在安全合规前提下，结合政务数据提升信用评估的准确性，降低信息不对称风险。"}
{"id": 662, "answer": ["D"]}
{"id": 655, "answer": ["A"]}
{"id": 658, "answer": "系统性金融风险的两大来源维度是顺周期累积和跨机构/跨市场/跨部门/跨境传染。其表现形式分别为顺周期波动（时间维度）和跨机构、跨市场、跨部门、跨境传染（结构维度）。"}
{"id": 660, "answer": ["D"]}
{"id": 659, "answer": ["B", "C", "D"]}
{"id": 663, "answer": ["C"]}
{"id": 667, "answer": "农村资金互助社解散的四种法定情形包括：（一）章程规定的解散事由出现；（二）社员大会决议解散；（三）因合并或者分立需要解散；（四）依法被吊销营业执照或者被撤销。"}
{"id": 666, "answer": ["A"]}
{"id": 668, "answer": ["B"]}
{"id": 665, "answer": ["B"]}
{"id": 664, "answer": "迁出方银行机构应及时通知相关存款人到本银行机构办理迁移失败单位银行结算账户的撤销手续。"}
{"id": 661, "answer": ["A", "B"]}
{"id": 671, "answer": ["A", "C"]}
{"id": 672, "answer": ["A"]}
{"id": 669, "answer": "外汇交易中心需采取以下措施确保业务连续性：1. 配备专用业务系统、网络和硬件设施（段落1、2）；2. 建立系统故障应急处理机制和灾难备份机制，确保数据安全与系统安全（段落1、2）；3. 健全内部控制机制、风险管理制度，定期进行风险分析（段落2）；4. 关键岗位实施复核与轮岗制度（段落2）；5. 制定业务连续性管理方案，包括高可用技术、数据备份策略及灾备中心建设（段落5）。"}
{"id": 653, "answer": ["C"]}
{"id": 670, "answer": ["D"]}
{"id": 673, "answer": ["B"]}
{"id": 638, "answer": ["B", "D"]}
{"id": 677, "answer": ["A", "C"]}
{"id": 674, "answer": ["B"]}
{"id": 675, "answer": ["B"]}
{"id": 678, "answer": "境外个人在境内购买商品房涉及的外汇管理遵循“合规性”和“真实性审核”原则，具体需按照《国家外汇管理局建设部关于规范房地产市场外汇管理有关问题的通知》等规定办理，并通过银行审核相关材料后办理购汇及对外支付手续。"}
{"id": 683, "answer": ["C"]}
{"id": 682, "answer": ["B"]}
{"id": 681, "answer": ["D"]}
{"id": 684, "answer": ["C"]}
{"id": 685, "answer": ["B"]}
{"id": 679, "answer": "全面防范银行卡境外交易中的洗钱风险需采取以下措施：1. **建立信息共享机制**，发卡银行和中国银联需及时报送不良持卡人及商户信息至“银行卡风险信息共享系统”（段落1）；2. **强化可疑交易监测**，对单月累计等值50万以上交易进行重点核查，并按要求向反洗钱监测中心报送交易明细及可疑交易报告（段落2）；3. **落实信息报送义务**，发卡行须按《银行卡境外交易外汇管理系统上线计划时间表》完成技术调整，实行零报送制度，未报送将面临监管处罚（段落3、段落4）；4. **加强国际合作与协作**，与境外反洗钱部门沟通，配合公安司法机关打击跨境非法资金转移（段落1）；5. **严格身份审查与合规管理**，按《人民币银行结算账户管理办法》等法规强化持卡人身份审核，确保交易合规性（段落5）。通过上述措施形成全链条风险防控体系。"}
{"id": 689, "answer": ["D"]}
{"id": 686, "answer": "企业在申请“银税互动”贷款前需完成以下授权程序：（1）授权税务部门依法向合作银行共享其纳税信息；（2）授权银行依法合规获取并使用其发票数据；（3）授权银行查询其涉税信息（若涉及）。这些授权需基于“依法合规”原则，并确保信息不被转卖或泄露。"}
{"id": 680, "answer": ["B"]}
{"id": 687, "answer": "商业银行代理销售投资连结型保险产品时，必须在设有销售专区的网点进行，并且严格限制在销售专区内。销售场所需满足“销售专区以上层级”的物理要求，且销售行为不得超出该专区范围。"}
{"id": 676, "answer": "金融机构协助制造业企业拆解担保圈风险的三项核心措施包括：1. 债委会“一企一策”并压降互保联保贷款比重（段落1）；2. 开展专项排查，实施名单式管理并制定“一户一策”风险处置预案（段落2）；3. 建立监测台账，综合运用措施拆圈解链（段落4）。"}
{"id": 688, "answer": ["C"]}
{"id": 692, "answer": ["B"]}
{"id": 697, "answer": ["C"]}
{"id": 691, "answer": []}
{"id": 690, "answer": "该地方商业银行需依据银监发200660号文件要求，立即停止发放商场购物卡（联名储值卡），对历史违规发放情况进行全面自查并整改，主动向银监会及其派出机构报告整改情况，接受专项检查。同时，需确保整改过程符合《中国人民银行关于加强银行卡业务管理的通知》（银发20145号）中关于银行卡业务管理的相关要求，避免涉及借记卡账户的违规操作。"}
{"id": 695, "answer": []}
{"id": 693, "answer": "发现可疑银行卡交易时，应按照以下步骤处理：1. 依据《金融机构反洗钱规定》等文件，严格执行大额交易和可疑交易报告制度（段落1）；2. 对可疑交易进行分类处理，选择“报送中国反洗钱监测分析中心”或“同时报送中心及当地分支机构”（段落2）；3. 金融机构需对可疑交易进行尽职调查并保留分析记录，若未报告但理由合理，可避免违规认定（段落3）；4. 中国银联应建立交易监控系统，协同调查处理异常交易，并通过风险信息共享机制防范风险（段落4）；5. 对来自监管薄弱国家或高风险地区的交易，需强化尽职调查并及时提交可疑交易报告（段落5）。"}
{"id": 694, "answer": ["C"]}
{"id": 704, "answer": ["C"]}
{"id": 701, "answer": ["B"]}
{"id": 698, "answer": ["D"]}
{"id": 696, "answer": ["A"]}
{"id": 700, "answer": "同一控制人下的两家境外机构需作为成员企业参与跨境资金集中运营管理备案，由主办企业统一提交备案材料。具体流程包括：1. 提交备案申请书，明确两家境外机构的注册文件（非中文需附中文翻译件）及股权结构；2. 提供跨国公司对主办企业的授权书；3. 签署合作银行确认书；4. 确保两家境外机构的控制关系符合受益所有人判定标准（如通过股权或协议控制）。最终备案需由主办企业向外汇局申请，确保两家机构的关联关系及合规性。"}
{"id": 702, "answer": "金融机构与非金融机构进行利率互换时需履行以下特别义务：（1）提示交易风险并避免欺诈误导（段落1第五条）；（2）未通过交易中心系统交易需在下一工作日12:00前备案（段落1第六条）；（3）将内部操作规程和风险管理制度报送交易商协会及交易中心备案（段落2第三条、段落3第三条）；（4）签订书面交易合同（段落1第七条、段落4第七条）；（5）违约时及时报告仲裁或诉讼结果并抄送交易中心（段落4第九条）；（6）确保交易符合非金融机构的资格限制（段落3第三条）。"}
{"id": 706, "answer": ["B"]}
{"id": 708, "answer": ["A"]}
{"id": 705, "answer": ["A"]}
{"id": 709, "answer": ["B"]}
{"id": 707, "answer": ["C"]}
{"id": 711, "answer": ["A", "B", "D"]}
{"id": 715, "answer": ["A", "C"]}
{"id": 713, "answer": ["B", "C"]}
{"id": 710, "answer": ["B"]}
{"id": 718, "answer": ["B"]}
{"id": 712, "answer": ["A", "C"]}
{"id": 703, "answer": ["A", "B"]}
{"id": 716, "answer": ["C", "D"]}
{"id": 720, "answer": ["B"]}
{"id": 719, "answer": ["B"]}
{"id": 721, "answer": ["B"]}
{"id": 717, "answer": ["D"]}
{"id": 723, "answer": ["A", "D"]}
{"id": 699, "answer": ["B"]}
{"id": 714, "answer": ["B", "C"]}
{"id": 728, "answer": ["B"]}
{"id": 724, "answer": "三类不符合绿色债券支持范围的隐性排除情形包括：1）存续期评估认证被出具“不符合”结论，导致绿色债券标识被撤销；2）评估报告无法发表结论，需重新评估，否则撤销标识；3）评估认证机构存在提交虚假材料、违反职业道德或报告重大遗漏等违规行为。"}
{"id": 730, "answer": ["C"]}
{"id": 729, "answer": ["C"]}
{"id": 727, "answer": ["C"]}
{"id": 731, "answer": ["C"]}
{"id": 732, "answer": "已达成的国债预发行合约在招标取消时原则上视为无效，但若交易双方在合同中另有约定（如约定违约责任或履约条款），则按约定处理。"}
{"id": 737, "answer": ["C"]}
{"id": 735, "answer": "同业存单的主要功能是为银行业存款类金融机构提供融资渠道，并促进货币市场的发展。"}
{"id": 736, "answer": ["C"]}
{"id": 734, "answer": ["D"]}
{"id": 739, "answer": ["C"]}
{"id": 738, "answer": ["B"]}
{"id": 742, "answer": ["B"]}
{"id": 740, "answer": "三类必须在交易前核验的人员资质清单包括：1. 是否涉及所在职机构经营中的重大关联交易；2. 是否涉及财务违法违规活动；3. 是否在所负责或参与的信贷业务流程中尽职尽责（参考段落3）。"}
{"id": 741, "answer": ["B", "C"]}
{"id": 744, "answer": ["C"]}
{"id": 743, "answer": ["B", "D"]}
{"id": 733, "answer": "申请设立船舶融资项目公司需满足以下基本要件：1）股东（大）会或董事会批准设立的决议；2）完善的内部控制机制及海外派驻人员背景说明；3）最近2年经审计的财务报告及财务报表；4）具备境外业务资质，且租赁物为船舶的需通过专业子公司开展业务；5）符合我国境外投资管理相关规定；6）提交主管部门批复、租赁合同及外汇合规材料（如报关单、发票等）。"}
{"id": 726, "answer": ["A", "B"]}
{"id": 750, "answer": ["B"]}
{"id": 722, "answer": ["B"]}
{"id": 725, "answer": []}
{"id": 747, "answer": ["C"]}
{"id": 751, "answer": ["A", "C"]}
{"id": 746, "answer": ["C"]}
{"id": 745, "answer": ["A", "B", "C"]}
{"id": 760, "answer": ["B", "C"]}
{"id": 752, "answer": ["A", "D"]}
{"id": 748, "answer": ["D"]}
{"id": 761, "answer": "施工企业在异地开立带项目部的临时账户时，需通过授权书明确约定“项目部因账户开立、使用和撤销而产生的所有法律责任由该建筑施工及安装单位承担”。这一约定是法律要求的必要条件，需在授权书中载明（依据段落1和段落3）。"}
{"id": 759, "answer": ["A", "C"]}
{"id": 755, "answer": ["B", "D"]}
{"id": 754, "answer": ["C"]}
{"id": 758, "answer": "券款对付结算模式的运作原理是，在结算日，债券和资金的交割实时同步进行，确保双方同时完成债券过户和资金划拨，实现最终一致且不可撤销的交收，从而降低信用风险。其适用场景包括需要严格履约保障的交易，如信用风险较高或交易规模较大的债券交易，以确保交易双方按约定足额交付债券和资金，避免单方面违约。"}
{"id": 749, "answer": "可能存在违规风险包括：1）资金用途偏离实体经济，导致信贷资源错配（段落3）；2）流动性风险加剧，机构资本充足率不足可能引发系统性风险（段落3）；3）资金集中导致异常流动，如短期内集中开户、资金频繁划转，可能涉及违规操作（段落2）；4）加工企业若存在重大诉讼、资产冻结等风险，可能影响贷款偿还（段落5）。整改措施应包括：1）严格审核贷款用途，确保用于农产品生产、加工等实际需求（段落4）；2）分散贷款投放，避免单一行业或企业集中（段落1、3）；3）加强资金流向监测，防范异常交易（段落2）；4）评估企业信用状况，控制高风险企业贷款（段落5）。"}
{"id": 753, "answer": ["C"]}
{"id": 764, "answer": ["B", "C"]}
{"id": 765, "answer": ["C"]}
{"id": 762, "answer": ["A", "C"]}
{"id": 766, "answer": ["C"]}
{"id": 767, "answer": "申请成为境外特约商户需提供法人和经办人的身份证、工商登记营业执照、税务登记证及相关纳税证明等基本材料（依据段落1和段落3）。"}
{"id": 772, "answer": ["B"]}
{"id": 770, "answer": ["A", "C"]}
{"id": 769, "answer": ["C"]}
{"id": 756, "answer": ["A", "B", "D"]}
{"id": 771, "answer": ["B"]}
{"id": 768, "answer": ["B"]}
{"id": 773, "answer": ["D"]}
{"id": 774, "answer": ["B"]}
{"id": 757, "answer": []}
{"id": 775, "answer": "个体工商户注销临时存款账户时应特别注意：1. 与开户银行核对账户存款余额；2. 交回所有重要空白票据及结算凭证；3. 若需在账户有效期届满前退还资金，须提供工商行政管理部门的证明；4. 确认无未清偿债务；5. 按规定提交相关证明文件（如营业执照等）。"}
{"id": 779, "answer": ["C"]}
{"id": 780, "answer": ["B", "D"]}
{"id": 777, "answer": ["B"]}
{"id": 778, "answer": "合格投资者应根据其股票和期货头寸的变化，动态调整外汇衍生产品敞口，确保其与外汇风险敞口保持合理相关度。当证券期货投资导致外汇风险敞口变化时，需及时调整外汇衍生产品敞口（依据段落2第二十一条第（二）项）。"}
{"id": 781, "answer": "信用卡分期付款业务的账单金额仅反映当期已出账的透支部分，而实际透支金额包含已出账单未偿还金额、未出账单部分（如分期付款未出账款项）及循环信用额度使用情况。因此，账单金额通常小于实际透支金额，尤其在分期付款未出账单时差异更为显著。"}
{"id": 782, "answer": ["C"]}
{"id": 783, "answer": "港澳人士一次性从内地银行支取超过5万元人民币现钞时，需办理登记手续（依据段落2第十三条）。"}
{"id": 785, "answer": ["C"]}
{"id": 786, "answer": ["C"]}
{"id": 784, "answer": "合格套期保值业务人员需具备以下岗位胜任力：1. 接受相关期货交易技能培训并取得从业资格；2. 具备至少1年期货交易经验；3. 熟悉套期会计操作程序及制度规范；4. 具备风险分析与管理能力；5. 业务主管需有2年以上交易或风险管理经验；6. 人员不得兼任，确保职责分离与合规操作。"}
{"id": 791, "answer": ["C"]}
{"id": 789, "answer": ["C"]}
{"id": 788, "answer": ["B", "C"]}
{"id": 793, "answer": "支付业务统计分析子系统的主要作用是从大额支付系统、小额支付系统和全国支票影像交换系统中采集、存储业务数据并进行加工处理，向用户提供查询、统计、分析等服务，以支持支付业务的监控与管理决策。"}
{"id": 792, "answer": ["B"]}
{"id": 776, "answer": ["B", "C"]}
{"id": 790, "answer": "申请网购支付银行账户需满足以下基础条件：1. 身份验证，需提供有效身份证件信息并通过银行核实；2. 账户数量限制，同一个人在同一家支付机构仅能开立一个Ⅲ类账户；3. 涉案账户管理，若账户被认定为涉案，需重新核实身份并暂停业务；4. 遵守支付账户分类管理规定，如Ⅲ类账户的限额及用途限制。"}
{"id": 795, "answer": ["C"]}
{"id": 794, "answer": ["A", "B"]}
{"id": 797, "answer": "政策性保险公司分支机构设立审批权限现归属于所在地银保监局。"}
{"id": 799, "answer": ["B", "D"]}
{"id": 796, "answer": ["B", "C"]}
{"id": 798, "answer": ["D"]}
{"id": 800, "answer": "金融机构申请变更电子商业汇票系统接入方式需经过以下流程：1. 以法人为单位向上海票据交易所提交书面变更申请，并遵循加入系统的程序（参考段落1第十八条、段落3第十八条）；2. 上海票据交易所在20个工作日内审核申请材料（段落3第十九条）；3. 通过审核后完成内部系统接入的实施工作（段落3第二十条）；4. 若涉及新业务开通、系统改造或物理环境变化，需重新申请验收（段落1第十九条），包括软件检测、信息系统检查及环境验收；5. 验收合格后确定上线切换日期并报备交易所（段落1第十九条）。"}
{"id": 804, "answer": ["A", "C", "D"]}
{"id": 803, "answer": ["C"]}
{"id": 805, "answer": ["B"]}
{"id": 802, "answer": "30个工作日"}
{"id": 801, "answer": ["A", "C"]}
{"id": 810, "answer": "代理开立的借记卡在被启用前仅支持存款转入等贷方交易，不支持取款、转出、消费、理财投资等借方交易。"}
{"id": 811, "answer": ["B"]}
{"id": 808, "answer": ["A", "C"]}
{"id": 806, "answer": "某银行被终止存取现金业务后，需满足以下条件和流程恢复业务：1. 等待一年后方可重新申请；2. 向人民银行分支机构提交申请并提供相关资料；3. 经人民银行验收合格，且需满足现金保管、清分质量、人员技能等业务规范要求；4. 通过审核后恢复业务。流程包括：申请→资料审核→验收→恢复。"}
{"id": 807, "answer": "银行业金融机构应从以下维度实施差别化信贷政策：1. **地区差异**（如住房价格调控目标、房地产市场状况）；2. **行业特征**（如钢铁煤炭等过剩产能行业）；3. **风险偏好与业务特征**（如负债管理指标、内部限额设置）；4. **客户类型**（如小微企业、涉农贷款）；5. **政策执行监督与动态调整**（如信息沟通、效果评估）。"}
{"id": 809, "answer": ["A", "B"]}
{"id": 812, "answer": "财务公司分阶段发行债券时，每次发行前需将发行方案报银监会备案（依据段落1和段落5）。"}
{"id": 787, "answer": ["B"]}
{"id": 813, "answer": "企业连续三个月核销报审率低于95%，将被外汇局取消签发港币支票的资格，并依据《中华人民共和国外汇管理条例》及相关规定接受处罚。"}
{"id": 814, "answer": ["C"]}
{"id": 818, "answer": "申请银行卡清算业务许可证的主要步骤包括：1. 准备符合要求的申请材料（如反洗钱制度方案、商标注册证、可行性研究报告等）；2. 向中国人民银行提交申请；3. 接受中国人民银行的审核；4. 通过审核后获得银行卡清算业务许可证。需注意，申请过程中需确保材料真实、符合反洗钱等监管要求，否则可能被拒或面临处罚。"}
{"id": 816, "answer": "发现银行卡疑似被盗刷时，应立即联系发卡银行挂失并申请冻结账户，同时向公安机关报案，保留交易记录等证据。根据段落3，银行需在24小时内上报案件至总行并启动内部应对措施；根据段落2，银监会与公安等部门协作打击非法买卖银行卡行为，需配合调查。此外，应避免泄露银行卡信息（如段落1所述安全防护要求），并及时向银监会或相关监管部门反馈情况。"}
{"id": 815, "answer": ["A", "C", "D"]}
{"id": 817, "answer": "货币经纪公司对合作机构的管理机制应包括以下核心环节：1. 设立独立合规部门，严格审查客户及交易机构资质，确保符合市场准入条件；2. 动态监测合作方报价及数据使用，避免错误信息传播；3. 制定数据服务规范，明确数据使用范围及出境安全管理；4. 按市场化原则与合作机构合作，统一收费标准并跟踪运营情况；5. 通过合规政策与董事会监督，确保合作机构行为符合监管要求。"}
{"id": 821, "answer": ["B"]}
{"id": 823, "answer": ["C"]}
{"id": 820, "answer": ["B"]}
{"id": 819, "answer": ["B"]}
{"id": 822, "answer": "金融机构通过系统性措施防范建设期风险，包括：（1）全面识别政策、完工、超支等风险并纳入评估报告；（2）要求项目资产抵押、预期收益质押及履约保函等担保措施；（3）根据风险特征设定差异化贷款利率；（4）设立专门收入账户监管资金用途；（5）通过总承包合同、财务顾问服务及专业中介机构（如法律、税务、环保等）提供综合风险缓释方案；（6）严格审核贷款支付进度与资本金到位情况，防止隐性债务风险。这些措施共同构成风险防控体系。"}
{"id": 830, "answer": ["B"]}
{"id": 825, "answer": "绿色债券与企业普通债券的核心区别在于：1）资金用途限定于绿色项目（如节能减排、资源节约等），需符合《绿色债券支持项目目录》；2）需通过第三方评估认证机构的审查与持续监督，普通债券无此强制要求；3）发行和存续期需遵循更严格的监管框架，如绿色债券标准委员会的管理，而普通债券的监管相对宽松。"}
{"id": 827, "answer": ["A", "C", "D"]}
{"id": 829, "answer": ["B", "C"]}
{"id": 824, "answer": ["A", "B"]}
{"id": 831, "answer": []}
{"id": 828, "answer": "商业银行通过以下措施约束发卡营销外包服务商的合规行为：1. 禁止转包或分包业务（段落1、3、4）；2. 要求外包服务商对申请人信息保密并不得违规使用资料（段落1、4）；3. 通过定期现场检查和风险评估监控外包业务（段落3、5）；4. 签订明确合同条款，明确安全责任边界（段落5）；5. 要求营销人员留存录音资料并保存至少2年（段落4）。"}
{"id": 832, "answer": ["B"]}
{"id": 826, "answer": ["A"]}
{"id": 836, "answer": ["B", "C"]}
{"id": 838, "answer": "城市商业银行资金清算中心成员机构的印章式样由其总行或资金清算中心确定并报中国人民银行总行备案，而非成员机构需自行确定式样并报所在地中国人民银行分支行备案。此外，成员机构可由清算中心统一组织刻制印章，而非成员机构需自行组织刻制。"}
{"id": 837, "answer": ["D"]}
{"id": 833, "answer": ["B", "D"]}
{"id": 834, "answer": ["B"]}
{"id": 839, "answer": "金融机构需在次年2月底前提交年度自评报告。"}
{"id": 840, "answer": ["B", "C", "D"]}
{"id": 841, "answer": ["B"]}
{"id": 845, "answer": ["B"]}
{"id": 844, "answer": ["A", "C"]}
{"id": 842, "answer": ["A", "C"]}
{"id": 835, "answer": ["A"]}
{"id": 843, "answer": "监管部门可采取的调查手段包括：1. 调取中国人民银行认可的交易报告库数据（如中国外汇交易中心的报告）；2. 核查境内清算机构向人民币跨境收付信息管理系统（RCPMIS）报送的跨境人民币收支信息；3. 调取境内电子交易平台和清算机构保存的交易数据、交流记录等。这些手段基于段落2、段落4及段落5中关于数据报告、保存义务和监管调取权限的描述。"}
{"id": 846, "answer": ["B"]}
{"id": 849, "answer": ["B"]}
{"id": 853, "answer": "外国银行分行改制为外商独资银行后，原有分行的营运资金经合并验资后可以转为外商独资银行的注册资本，或转回其总行。"}
{"id": 848, "answer": ["B"]}
{"id": 851, "answer": ["B"]}
{"id": 847, "answer": "证券出借业务需同步落实的持续风险管理措施包括：动态监控担保比例并确保持续达标（段落1）；定期对流动性风险、信用风险、市场风险和交易对手集中度风险进行压力测试（段落1、4）；对交易额度实施动态管理和调整（段落2、4）；将出借证券纳入托管范围并签订托管合同（段落2、5）；加强关联交易管理，确保交易公平合理（段落2）；定期将证券出借情况纳入季度/年度报告，包含担保水平、风险评估等（段落3）；发生重大风险事件时及时采取控制措施并报告（段落3）；出借期限超过20个交易日的证券不纳入流动性监测比例（段落4、5）。"}
{"id": 852, "answer": ["A", "B"]}
{"id": 855, "answer": ["C"]}
{"id": 854, "answer": ["A", "B"]}
{"id": 859, "answer": []}
{"id": 858, "answer": ["B"]}
{"id": 763, "answer": []}
{"id": 856, "answer": ["A", "C"]}
{"id": 850, "answer": ["C"]}
{"id": 857, "answer": "不合规。理由包括：1. 根据《人民币银行结算账户管理办法》，单位向个人账户转账需审查付款依据，否则银行应拒绝办理；2. 储蓄账户禁止转账，若员工账户为储蓄账户则直接违规；3. 段落1明确“利用员工账户过渡资金”属于违规行为，可能涉及出借账户或资金过渡。因此，此类操作通常不符合合规要求。"}
{"id": 869, "answer": ["B"]}
{"id": 861, "answer": "银行柜员应首先核查临时身份证是否在有效期内（有效期为三个月）。通过联网核查系统比对证件有效期截止日期，若系统反馈“有效期不一致”，则视为证件无效。此时，柜员需要求客户提供其他辅助身份证明材料（如护照、驾驶证等），或根据段落4采取进一步核实措施，若无法确认证件有效性则拒绝办理业务。"}
{"id": 867, "answer": ["C"]}
{"id": 868, "answer": "境外机构投资者可通过开展境内人民币对外汇衍生产品交易（如远期、期权等）进行套期保值，管理外汇风险敞口；同时可选择托管人、结算代理人或直接进入银行间外汇市场交易，利用即期结售汇和衍生品工具对冲风险。此外，鼓励使用人民币跨境结算以减少汇率波动影响。"}
{"id": 866, "answer": ["B"]}
{"id": 870, "answer": ["C"]}
{"id": 864, "answer": "当电子银行转账出现异常登录提醒时，应立即采取以下措施：1. 确认是否为自身操作，检查是否有可疑活动；2. 若确认非本人操作，立即通过银行官方渠道冻结账户并更改密码；3. 联系银行客服核实登录异常，启用动态验证码、短信验证等额外身份验证方式；4. 检查账户交易记录，防范资金风险；5. 遵循银行提示，配合完成风险排查。银行方面应通过监控登录次数、强化身份验证、建立预警机制（如段落1第五条）等手段防范风险。"}
{"id": 873, "answer": ["B", "D"]}
{"id": 860, "answer": ["B"]}
{"id": 863, "answer": ["A", "C"]}
{"id": 865, "answer": ["C"]}
{"id": 872, "answer": ["D"]}
{"id": 871, "answer": "债券交易流通服务的全链条参与主体至少包括发行人或主承销商、债券登记托管结算机构（中央国债登记结算有限责任公司和银行间市场清算所股份有限公司）、同业拆借中心、中国人民银行及市场参与者（如商业银行、非银行金融机构等）。"}
{"id": 862, "answer": []}
{"id": 875, "answer": ["B"]}
{"id": 876, "answer": ["A"]}
{"id": 874, "answer": ["A", "B", "C", "D"]}
{"id": 877, "answer": ["C"]}
{"id": 878, "answer": ["C"]}
{"id": 879, "answer": ["A", "C"]}
{"id": 881, "answer": ["A", "C"]}
{"id": 888, "answer": ["D"]}
{"id": 883, "answer": "区域性信用信息平台需整合金融、税务、市场监管、社保、海关、司法及征信等领域的政务数据。"}
{"id": 882, "answer": ["D"]}
{"id": 889, "answer": ["D"]}
{"id": 880, "answer": ["B"]}
{"id": 891, "answer": ["C"]}
{"id": 886, "answer": ["B"]}
{"id": 885, "answer": "优化农村中小金融机构的外源性资本补充渠道应通过以下措施：1. 鼓励配股、定向募集等股权融资方式；2. 发行符合新监管标准的债务工具（如优先股、可转债等）；3. 开展合格资本工具创新试点（如永续债、减记债等）；4. 优化融资结构，降低融资成本（如通过债务工具创新和资本配置优化）。这些措施可结合段落1和段落3的政策导向，推动多元化、低成本的外源性资本补充。"}
{"id": 884, "answer": "企业需同步达成以下法律程序：（1）在停售期间无其他重大失信行为；（2）缴清所有罚款或配合银行完成核实；（3）银行审核通过并解除限售措施；（4）与银行签订并履行支票服务协议。"}
{"id": 890, "answer": "当日10:00。"}
{"id": 892, "answer": ["B"]}
{"id": 894, "answer": ["A", "B", "D"]}
{"id": 898, "answer": ["D"]}
{"id": 896, "answer": ["A", "C", "D"]}
{"id": 897, "answer": ["B", "C"]}
{"id": 895, "answer": "债券预发行交易发生违约纠纷时，投资者应通过仲裁或诉讼解决争议，并在收到最终结果的下1个工作日12:00前将结果提交交易中心和债券登记托管结算机构公告（依据段落1第十八条）。同时，交易中心和登记托管机构需及时披露相关信息，防范风险并向中国人民银行及相关部门报告异常情况（依据段落1第十七条）。纠纷处理规则由央行监管框架内实施，具体操作需遵循《全国银行间债券市场债券预发行业务管理办法》的相关规定。"}
{"id": 903, "answer": ["B"]}
{"id": 900, "answer": ["B", "C"]}
{"id": 899, "answer": ["C"]}
{"id": 902, "answer": ["B", "D"]}
{"id": 887, "answer": ["B"]}
{"id": 904, "answer": ["B"]}
{"id": 893, "answer": ["D"]}
{"id": 905, "answer": "新型结构化回购产品需额外披露的要素包括：结构化融资产品的评级方法、评级模型及关键假设（依据段落3第四十四条），以及持续更新的评级信息（依据段落5第六章）。此外，若涉及信用风险缓释工具，需符合相关条件（如信用风险缓释工具的到期日不早于基础资产最晚到期日等，依据段落2）。"}
{"id": 909, "answer": ["C"]}
{"id": 906, "answer": "不可能发生。"}
{"id": 901, "answer": "单位代理开立的个人银行账户在激活前仅支持“只收不付”操作，即允许接收资金（如存款、转账等贷方交易），但禁止支付、取款、消费等借方交易，直至被代理人持本人有效身份证件到银行完成身份确认、密码设（重）置等激活手续。"}
{"id": 911, "answer": ["A", "C", "D"]}
{"id": 913, "answer": ["B"]}
{"id": 912, "answer": "成员银行退出联合授信委员会的两种途径是：（1）主动退出，即当成员银行对企业融资余额为零时，可主动申请退出；（2）自动退出，即连续12个月对企业融资余额为零的成员银行，将自动退出该企业的联合授信委员会。"}
{"id": 915, "answer": ["A", "B"]}
{"id": 916, "answer": ["C"]}
{"id": 914, "answer": ["C"]}
{"id": 910, "answer": ["B", "C"]}
{"id": 917, "answer": ["A", "C"]}
{"id": 907, "answer": "商业银行防范信用卡套现需协同控制的三类主体及措施包括：  \n1. **持卡人**：加强用卡行为监控，对确认套现行为采取降低授信额度、止付等措施；  \n2. **发卡营销外包服务商**：禁止转包业务，确保申请人信息保密，防止虚假申请；  \n3. **特约商户**：设置交易金额上限，禁止集中刷卡套现，规范退票等操作流程。"}
{"id": 908, "answer": ["C"]}
{"id": 918, "answer": ["B"]}
{"id": 925, "answer": ["D"]}
{"id": 924, "answer": ["B", "C"]}
{"id": 919, "answer": ["C"]}
{"id": 929, "answer": ["B"]}
{"id": 922, "answer": "商业银行在个人养老金产品代销业务中需建立的配套管理制度包括：合作机构管理、产品准入管理、投资人适当性管理、销售管理、全面风险管理、信息披露与保密管理、投诉和应急处理机制、销售系统支持、利益冲突防范机制以及消费者权益保护机制。这些制度需覆盖产品合规性、风险控制、客户服务及公平交易等核心环节。"}
{"id": 926, "answer": "商业银行需落实的风控措施包括：制定内控及风险管理制度并规范操作流程（段落5第四条）、足额计提减值准备并遵循资本计提规则（段落1第三条）、在风险可控和商业可持续前提下开展交易（段落5第二条），以及遵守监管机构关于债券交易的最新规定（段落5第五条）。"}
{"id": 921, "answer": []}
{"id": 928, "answer": ["A", "B"]}
{"id": 930, "answer": ["B"]}
{"id": 920, "answer": ["A"]}
{"id": 927, "answer": ["B"]}
{"id": 932, "answer": []}
{"id": 931, "answer": ["B"]}
{"id": 935, "answer": ["A", "D"]}
{"id": 934, "answer": ["C"]}
{"id": 933, "answer": ["A", "C"]}
{"id": 939, "answer": ["B"]}
{"id": 938, "answer": ["B"]}
{"id": 937, "answer": ["A", "D"]}
{"id": 923, "answer": ["B", "C"]}
{"id": 942, "answer": ["A"]}
{"id": 943, "answer": ["B"]}
{"id": 941, "answer": ["B"]}
{"id": 940, "answer": ["C"]}
{"id": 946, "answer": "信托财产专户的存款人名称应以受托人（即信托投资公司）的全称为标准命名。"}
{"id": 947, "answer": ["B", "C"]}
{"id": 948, "answer": ["B"]}
{"id": 951, "answer": ["A"]}
{"id": 950, "answer": ["B"]}
{"id": 953, "answer": ["B"]}
{"id": 936, "answer": "境内托管账户、信托专用证券账户、信托专用资金账户。"}
{"id": 952, "answer": ["B"]}
{"id": 945, "answer": ["B", "C"]}
{"id": 957, "answer": ["A", "C", "D"]}
{"id": 944, "answer": ["A"]}
{"id": 958, "answer": ["C"]}
{"id": 949, "answer": "境外机构投资者同时使用人民币和外汇投资时，外币资金的汇出入需遵守以下限制：1. 外币资金需先结汇划入对应的人民币专用账户，不得直接在人民币专用账户与外币专用账户间划转资金；2. 汇出外币金额不得超过累计汇入外币金额的1.2倍（投资清盘汇出除外）；3. 不得进行人民币与外币之间的跨币种套利；4. 投资本金和收益可选择外币或人民币汇出，但需符合上述比例及币种管理要求。"}
{"id": 960, "answer": ["B", "D"]}
{"id": 961, "answer": ["C"]}
{"id": 955, "answer": "金融机构需在报送案件报告后一年内提交整改报告，逾期可申请延期（每次不超过六个月）。若案件报告后两年内未完成审结，监管部门将视情节采取监管约谈、责令整改等措施。"}
{"id": 956, "answer": "当关键期限国债流动性显著恶化时，做市商需在遵守《全国银行间债券市场做市商管理规定》及《关于新发关键期限国债做市有关事宜的公告》要求（如连续双边报价、选择指定券种）的前提下，动态调整报价策略以增强市场流动性，同时利用监管支持措施（如中国人民银行的技术系统优化）和风险对冲工具，平衡合规性与风控需求。"}
{"id": 962, "answer": ["C"]}
{"id": 954, "answer": ["C", "D"]}
{"id": 963, "answer": ["C"]}
{"id": 966, "answer": "判定手机银行客户端是否为监管认可的自营网络平台，需依据以下标准：（1）平台是否由商业银行自主运营（非第三方合作平台），符合《关于规范商业银行通过互联网开展个人存款业务有关事项的通知》（银保监办发〔2021〕9号）要求；（2）客户端需通过数字签名验证来源，确保其为可信机构发布（参考段落2）；（3）平台业务需符合监管对存款、支付等金融活动的合规性要求。若平台满足上述条件，则可判定为监管认可的自营网络平台。"}
{"id": 967, "answer": ["A", "B"]}
{"id": 971, "answer": ["B"]}
{"id": 970, "answer": ["A", "B"]}
{"id": 969, "answer": ["C"]}
{"id": 964, "answer": ["A", "B"]}
{"id": 968, "answer": "外资银行分行需满足以下基本准入条件：1. 向中国人民银行提交《中国银行间市场投资备案表》（段落1、段落2）；2. 作为长期投资者，基于资产保值增值需求开展交易（段落1）；3. 委托具备国际结算能力的银行间市场结算代理人进行交易和结算，并签署结算代理协议（段落1、段落3）；4. 具备风险识别和承担能力，自行承担债券投资风险（段落3）；5. 符合中国人民银行规定的其他条件（段落3）。"}
{"id": 959, "answer": "监管部门会认定银行正确执行规定，因临时居民身份证的有效期为三个月，客户持有的“有效期两个月”的旧版临时身份证不符合规定，银行拒绝开卡属于合规行为。"}
{"id": 978, "answer": ["A", "C"]}
{"id": 972, "answer": "储户遗失教育储蓄存折需立即持本人身份证明（如户口簿或居民身份证），并提供姓名、开户时间、储蓄种类、金额、账号及住址等信息，向开户机构书面申请挂失。无需额外提交教育相关证明，但需注意教育储蓄的实名制要求（开户时已提交的证件信息可能作为身份验证依据）。"}
{"id": 965, "answer": ["B"]}
{"id": 979, "answer": ["B", "D"]}
{"id": 976, "answer": ["C"]}
{"id": 973, "answer": ["B"]}
{"id": 980, "answer": "电子印章推广的主要技术手段包括建立电子化印章管理机制和配套信息系统、推广使用印控机等电子机具、采用加密、认证及远程监控等技术防控措施。"}
{"id": 983, "answer": ["A", "C"]}
{"id": 974, "answer": ["B"]}
{"id": 981, "answer": ["C"]}
{"id": 984, "answer": ["A", "C"]}
{"id": 977, "answer": ["C"]}
{"id": 982, "answer": "银行应通过以下因素确定客户的实际贷款利率：1. 资金成本、业务成本、风险成本；2. 客户的综合贡献度及客户关系；3. 贷款方式、期限等具体条件；4. 市场水平（如当地同类机构贷款利率）；5. 法定利率基准及协商机制（如信托贷款、转贷款利率的协商）。"}
{"id": 988, "answer": ["D"]}
{"id": 989, "answer": ["C"]}
{"id": 990, "answer": "银行应首先核实客户身份真实性，若确认为非实名号码或存在可疑交易，有权暂停账户使用并要求客户更新实名手机号；同时需提高风险评级，加强交易监控，分析资金流动是否涉及电信诈骗、洗钱或非法集资，并按反洗钱规定向监管机构报告可疑交易。"}
{"id": 987, "answer": ["B"]}
{"id": 993, "answer": ["C"]}
{"id": 985, "answer": ["C"]}
{"id": 994, "answer": ["A", "C"]}
{"id": 998, "answer": ["C"]}
{"id": 1000, "answer": ["A", "C"]}
{"id": 986, "answer": ["B"]}
{"id": 997, "answer": ["B"]}
{"id": 996, "answer": ["B", "D"]}
{"id": 999, "answer": ["A", "B", "C"]}
{"id": 995, "answer": ["D"]}
{"id": 1001, "answer": ["A"]}
{"id": 1003, "answer": ["A"]}
{"id": 1005, "answer": ["A", "C", "D"]}
{"id": 1007, "answer": ["B"]}
{"id": 1002, "answer": "开通电话银行需客户预留本人实名登记的手机号码，若涉及高风险操作（如大额转账），可能需额外提供CVV码、身份证信息或其他预注册信息作为验证。"}
{"id": 1006, "answer": ["B"]}
{"id": 1004, "answer": ["D"]}
{"id": 1008, "answer": "教育储蓄到期支取时需携带存折和学校开具的“正在接受非义务教育的学生身份证明”（即“证明”原件），方可享受利率优惠及免征利息所得税的全部福利。"}
{"id": 975, "answer": ["C"]}
{"id": 1010, "answer": ["B"]}
{"id": 992, "answer": ["C"]}
{"id": 1012, "answer": ["B"]}
{"id": 1009, "answer": "应遵循《绿色债券支持项目目录（2015年版）》。因为该企业2021年6月发行的债券已完成注册程序，根据段落4，目录发布前已核准或注册的债券仍按2015年版执行，而2021年7月1日后的目录修订不适用于已注册项目。"}
{"id": 1017, "answer": ["C"]}
{"id": 1011, "answer": "保险保障基金对超过5万元部分的救助比例存在差异：个人保单持有人获赔90%，机构保单持有人获赔80%。特殊情形包括投资成分的救助办法另行制定、国务院可调整救助比例，以及债权转让和清偿顺序的特殊处理。"}
{"id": 1019, "answer": ["B"]}
{"id": 1016, "answer": ["C"]}
{"id": 1015, "answer": "同业专营部门与境外子公司的业务协作边界及防火墙建设要点包括：  \n1. **业务边界**：同业专营部门负责同业业务的集中审批、风险承担及独立运营，境外子公司需在跨境资金集中运营中遵循统一授信与合规管理，避免与专营部门的业务交叉。  \n2. **防火墙建设**：  \n   - **授权与独立性**：同业专营部门需由法人总部统一授权，禁止转授权；业务操作与自营业务分离，系统、人员、制度独立（段落2、3）。  \n   - **风险隔离**：建立集团统一风险视图，防范跨境、跨业风险传染，规范人员交叉任职，定期审计并表管理有效性（段落1）。  \n   - **合规与监控**：跨境资金管理需联合制定内控制度，强化数据监测与合规审核，避免利益输送（段落4）。  \n   - **授信与准入**：统一授信政策，动态管理交易对手名单，杜绝多头授信与无额度业务（段落2、3）。"}
{"id": 1020, "answer": ["C"]}
{"id": 1018, "answer": "联合授信额度复评时需考量的核心要素包括资产负债水平、利润及其增长率、经营现金流、所属行业、所在区域、还款历史、经营年限、企业实际融资总额、对外担保情况及剩余融资额度。这些要素需结合企业经营和财务变化重新评估，并确保实际融资不超过确认的额度。"}
{"id": 991, "answer": ["C"]}
{"id": 1013, "answer": ["B", "D"]}
{"id": 1022, "answer": ["B"]}
{"id": 1021, "answer": ["C"]}
{"id": 1025, "answer": ["C"]}
{"id": 1023, "answer": ["C"]}
{"id": 1029, "answer": ["D"]}
{"id": 1031, "answer": ["B"]}
{"id": 1024, "answer": ["A", "B"]}
{"id": 1026, "answer": ["B"]}
{"id": 1032, "answer": ["A"]}
{"id": 1034, "answer": ["B"]}
{"id": 1028, "answer": ["B", "C"]}
{"id": 1014, "answer": ["A"]}
{"id": 1027, "answer": ["B"]}
{"id": 1030, "answer": ["A", "C"]}
{"id": 1037, "answer": ["B"]}
{"id": 1035, "answer": ["C"]}
{"id": 1033, "answer": ["B"]}
{"id": 1041, "answer": ["A", "C", "D"]}
{"id": 1042, "answer": ["D"]}
{"id": 1044, "answer": ["D"]}
{"id": 1045, "answer": ["B"]}
{"id": 1039, "answer": ["D"]}
{"id": 1046, "answer": ["C"]}
{"id": 1038, "answer": []}
{"id": 1048, "answer": ["C"]}
{"id": 1050, "answer": ["D"]}
{"id": 1051, "answer": ["C"]}
{"id": 1043, "answer": ["C"]}
{"id": 1049, "answer": ["B"]}
{"id": 1047, "answer": []}
{"id": 1054, "answer": ["B", "C"]}
{"id": 1052, "answer": "1家"}
{"id": 1053, "answer": ["A", "B", "D"]}
{"id": 1055, "answer": ["C"]}
{"id": 1057, "answer": ["B"]}
{"id": 1058, "answer": "银联卡境外业务迁移过渡期内允许同时保留境内和境外清算代理行的外币清算账户。"}
{"id": 1056, "answer": "银行应依据银保监会“一行一策”原则制定整改方案，确保第三方平台存款业务平稳过渡，保障消费者权益；同时主动排查历史遗留问题并及时纠正，避免监管扣分；需强化对第三方平台合作的统一管理，完善合规制度流程，确保业务符合监管要求。"}
{"id": 1063, "answer": ["A", "C"]}
{"id": 1036, "answer": ["D"]}
{"id": 1064, "answer": ["A"]}
{"id": 1061, "answer": ["A", "B", "D"]}
{"id": 1059, "answer": "支付机构需在扫码APP客户端嵌入以下基础安全功能：1. 防逆向工程保护（代码混淆、反调试）；2. 软件完整性校验（签名验证、启动/更新时真伪检测）；3. 运行时安全防护（木马防范、信息加密、运行环境可信）；4. 通信安全（SSL/TLS双向认证、抗抵赖数字签名）；5. 数据有效性校验与敏感信息清除机制；6. 交易密码加密、复杂度校验及独立支付密码设置；7. 支付环境安全监测与异常处理功能。"}
{"id": 1060, "answer": "有效盘活现有公路资产以提高流动性需采取以下措施：1. 通过资产证券化（ABS）、基础设施REITs等金融工具实现存量资产证券化；2. 优化还款安排，设置建设期加1年的宽限期缓解初期现金流压力；3. 引入保险资金、地方政府债券等多元化融资渠道，支持项目建设与债务化解；4. 实行分账管理，将专项收入优先用于偿还融资，确保资金安全；5. 优化贷款条件，避免盲目抽贷断贷，保障企业持续运营能力。这些措施可协同提升公路资产的流动性与资金使用效率。"}
{"id": 1068, "answer": ["D"]}
{"id": 1071, "answer": ["B"]}
{"id": 1066, "answer": ["B"]}
{"id": 1065, "answer": "重大工程项目贷后管理需关注的风险信号包括：1. 借款人或项目发起人的信用状况恶化；2. 项目建设进度滞后或运营异常；3. 宏观经济波动或市场环境变化影响项目收益；4. 贷款担保物价值变动或担保能力减弱；5. 分级预警信号（红色：直接威胁资金安全，需暂停新增授信；橙色：需压缩授信额度；黄色：需维持性监控）。此外，需持续监测项目收入账户及履约义务人信用评分变化。"}
{"id": 1067, "answer": "不会受到影响。因为2024年9月27日的存款准备金率调整仅针对跨省经营的城市商业银行，而仅在省内运营的城市商业银行的存款准备金率已固定为6%（根据段落3），因此不受此次调整影响。"}
{"id": 1070, "answer": ["C"]}
{"id": 1073, "answer": ["A", "C"]}
{"id": 1062, "answer": ["B"]}
{"id": 1074, "answer": ["B"]}
{"id": 1072, "answer": ["B"]}
{"id": 1075, "answer": ["C"]}
{"id": 1080, "answer": ["B"]}
{"id": 1077, "answer": ["B"]}
{"id": 1076, "answer": "不会受到影响。因为2024年9月27日的存款准备金率调整仅针对跨省经营的城市商业银行，而仅在省内运营的银行未被纳入调整范围，其准备金率可能仍按原有标准（如段落3所述的6%）执行。"}
{"id": 1069, "answer": ["D"]}
{"id": 1079, "answer": ["A"]}
{"id": 1078, "answer": "商业银行通过设定“三农”专项金融债募集资金期限不少于3年（段落1、4），确保资金覆盖农业生产经营周期；同时建立专户管理、资金流向监测及定期考核机制（段落2、4），确保资金专用于涉农贷款，避免提前回收或挪用；并健全信贷风险管理体系（段落1），以实现长期资金与农业生产周期的匹配。"}
{"id": 1084, "answer": ["C"]}
{"id": 1081, "answer": ["D"]}
{"id": 1082, "answer": ["D"]}
{"id": 1086, "answer": ["C"]}
{"id": 1087, "answer": "信托计划未成功设立时，信托投资公司应将信托财产专户中的资金余额及时返还给原委托人，并按约定加计银行同期存款利息。"}
{"id": 1083, "answer": "外资银行需满足以下要求：1. 配备业务人员、安全设施及内部控制制度，并提交人民币业务筹备情况说明；2. 股东资质合规，治理无重大缺陷；3. 增加注册资本需验资并提交证明；4. 分行需获得总行授权；5. 严格审核客户购售业务真实性（参照段落1、2、5）。"}
{"id": 1088, "answer": ["C"]}
{"id": 1085, "answer": ["B"]}
{"id": 1092, "answer": ["C"]}
{"id": 1089, "answer": ["A", "B", "D"]}
{"id": 1094, "answer": ["C"]}
{"id": 1093, "answer": ["C", "D"]}
{"id": 1091, "answer": "更换个人养老金资金账户开户行时，需遵循以下特别规定：1. 资金账户具有唯一性，参加人只能选择一家符合条件的商业银行开立或指定（段落1第十八条）；2. 更换开户行需通过商业银行指定渠道办理变更服务（段落3第十四条）；3. 若原开户行因解散、被撤销等原因终止，资金账户及资金应转让给其他符合条件的商业银行，或由银保监会协调转至其他机构（段落5第五十九条）；4. 所有资金交易必须通过新账户发起并返回，确保交易连续性（段落1第十六条）。"}
{"id": 1097, "answer": ["C"]}
{"id": 1098, "answer": ["C"]}
{"id": 1090, "answer": ["A", "B", "C", "D"]}
{"id": 1096, "answer": "债券远期交易中保证金管理的两种模式及其对应的利率规则为：（1）交易双方自行保管的保证金，其利率按放开金融机构同业存款利率政策执行，利率水平及付息方式由双方协商确定；（2）集中保管的保证金，利率由托管机构统一执行（具体规则可能依据市场利率或托管机构政策）。"}
{"id": 1100, "answer": ["A"]}
{"id": 1099, "answer": ["C"]}
{"id": 1101, "answer": "重新确定结算日期需依据成交双方事先约定的处置方式（如段落2所述），并结合突发事件应急处置机制（段落1）调整。需提前约定的风控条款包括：1）应急结算安排（如NRA账户）；2）资源池机制以管理跨境风险敞口；3）交易对手信用风险管理（段落4）；4）操作风险控制措施（段落4）。"}
{"id": 1103, "answer": ["A", "C", "D"]}
{"id": 1104, "answer": ["B"]}
{"id": 1107, "answer": ["B", "C"]}
{"id": 1040, "answer": ["B", "D"]}
{"id": 1108, "answer": ["B"]}
{"id": 1095, "answer": ["C", "D"]}
{"id": 1106, "answer": "办理存单质押必须完成的法定程序包括：签订书面质押合同、办理存单确认和止付手续、存单挂失补办、约定质押合同条款、妥善保管质押存单、禁止擅自动用存单及贷款期满后注销登记。"}
{"id": 1109, "answer": ["B", "D"]}
{"id": 1117, "answer": ["C"]}
{"id": 1102, "answer": ["B", "D"]}
{"id": 1115, "answer": ["C"]}
{"id": 1111, "answer": ["A"]}
{"id": 1112, "answer": "定期储蓄存单在存期内遇到央行调息时，收益不受影响，仍按存单开户日挂牌公告的定期储蓄存款利率计付利息。"}
{"id": 1110, "answer": ["C"]}
{"id": 1114, "answer": ["B", "D"]}
{"id": 1118, "answer": ["A"]}
{"id": 1120, "answer": ["A", "B"]}
{"id": 1119, "answer": ["C", "D"]}
{"id": 1113, "answer": ["B", "C"]}
{"id": 1123, "answer": ["C"]}
{"id": 1124, "answer": ["A", "C"]}
{"id": 1122, "answer": ["B"]}
{"id": 1125, "answer": ["A", "C"]}
{"id": 1127, "answer": "中国人民银行未采纳限制投资者在双重市场开户的政策，主要原因是允许投资者根据自身需求选择在银行间债券市场和柜台市场同时开户，这种多元化选择能够通过市场竞争提升整体市场运行效率，从而促进债券市场的健康发展。"}
{"id": 1128, "answer": ["B"]}
{"id": 1129, "answer": ["A", "B", "C", "D"]}
{"id": 1121, "answer": ["B"]}
{"id": 1116, "answer": ["A", "C"]}
{"id": 1131, "answer": "保险集团公司下属子公司之间不得相互认购资本补充债券，这一限制由段落1第十四条明确规定。"}
{"id": 1132, "answer": ["A", "B", "D"]}
{"id": 1126, "answer": "创新型衍生产品上线前的合规审查链条应包含以下环节：1. 与监管部门沟通并书面咨询意见（段落1）；2. 建立内部管理制度，包括交易操作规程（前台、中台、后台分离）、风险模型指标、风险控制制度、内部审计制度、应急计划、交易员守则、岗位责任制度及培训计划（段落2）；3. 风险敞口量化或限额的授权管理制度（段落2）；4. 交易品种及其风险控制制度（段落2）；5. 盯市管理制度（段落2）；6. 事前可行性研究及风险评估（段落5）。"}
{"id": 1134, "answer": ["C"]}
{"id": 1135, "answer": ["B"]}
{"id": 1133, "answer": ["A", "B"]}
{"id": 1136, "answer": "金融债券发行后十个工作日内，发行人需向中国人民银行书面报告当期金融债券发行情况，承销商需报告当期债券承销情况。"}
{"id": 1140, "answer": ["D"]}
{"id": 1105, "answer": ["C"]}
{"id": 1137, "answer": "当储户遭遇疑似非正规操作提示时，应首先关注银行通过短信、电话或APP推送等渠道发出的交易风险提示（如大额交易、短时高频交易等），并及时联系银行客服或前往网点核实交易真实性。同时，需检查账户安全，如修改交易密码、避免使用简单密码（参考段落2），并保留相关凭证以备查询。若确认存在异常操作，应立即冻结账户并报警处理。"}
{"id": 1142, "answer": ["A", "C", "D"]}
{"id": 1143, "answer": ["A", "C"]}
{"id": 1141, "answer": ["A"]}
{"id": 1147, "answer": ["C"]}
{"id": 1145, "answer": ["C"]}
{"id": 1138, "answer": ["A", "B", "D"]}
{"id": 1146, "answer": ["B"]}
{"id": 1148, "answer": ["C"]}
{"id": 1130, "answer": ["A", "C"]}
{"id": 1144, "answer": ["B", "C"]}
{"id": 1149, "answer": "金融机构在处理单位存款时，若未全额划缴中国人民银行的财政存款，未划缴部分需按单位存款利率计息（依据段落3第十八条）。"}
{"id": 1156, "answer": ["C"]}
{"id": 1154, "answer": "商业银行申请做市商资格的操作流程包括：1. 向证券交易所提交债券交易做市商资格申请；2. 在申请时同步向银监会书面报告；3. 遵守银监会关于资本计提、报表填报等监管要求，并按交易所规定执行做市交易。具体申请材料需参照交易所相关规定，但银监会要求试点银行及时准确报送数据。"}
{"id": 1153, "answer": ["B", "D"]}
{"id": 1151, "answer": "金融机构申请进入同业拆借市场的基本条件包括：（1）在中华人民共和国境内依法设立；（2）具备健全的同业拆借交易组织机构、风险管理制度和内部控制制度；（3）配备专门从事同业拆借交易的人员；（4）主要监管指标符合中国人民银行和有关监管部门的规定；（5）最近两年未因违法、违规行为受到中国人民银行和有关监管部门处罚；（6）最近两年未出现资不抵债情况；（7）中国人民银行规定的其他条件。此外，不同类别的金融机构还需满足特定财务要求，如证券公司需最近两个年度连续盈利且净资本不低于2亿元，保险公司需最近四个季度偿付能力充足率在120%以上等。"}
{"id": 1152, "answer": ["A", "B", "C", "D"]}
{"id": 1155, "answer": "创新型小微金融服务模式至少应包括以下要素：1. 科技保障（如客户信息管理系统、数据分析与挖掘）；2. 差异化服务（细分客户群体，提供定制化方案）；3. 综合金融产品（如知识产权质押贷款、信用贷款、股权质押贷款）；4. 风险评估与管理机制（结合企业核心技术、创新能力及潜在风险）；5. 合作网络（与产业园区、投资基金、保险机构等协同）；6. 激励约束机制及合规经营体系。"}
{"id": 1160, "answer": ["B"]}
{"id": 1150, "answer": ["A"]}
{"id": 1158, "answer": ["A", "B", "D"]}
{"id": 1159, "answer": ["C"]}
{"id": 1139, "answer": []}
{"id": 1165, "answer": ["C"]}
{"id": 1161, "answer": ["A"]}
{"id": 1163, "answer": ["B"]}
{"id": 1164, "answer": ["B"]}
{"id": 1172, "answer": "支付机构年度监管报告中财务分析模块需揭示的关键维度包括：（1）资产负债分析，涵盖流动性冲击应对能力、客户备付金安全保障及风险准备金计提；（2）盈亏状况，明确各类支付业务盈利状况及主要盈利来源；（3）资本充足分析，反映实收资本充足性及实缴货币资本与客户备付金余额的比例。"}
{"id": 1169, "answer": "辨别正规货币鉴定机构的合法资质需核查以下要点：1. 是否持有中国人民银行颁发的《中国人民银行授权书》并公示；2. 是否具备2名以上专业鉴定人员及满足技术条件的设备；3. 是否拥有固定鉴定场所；4. 是否公示授权证书及业务范围；5. 是否按规范出具《货币真伪鉴定书》并加盖专用章。可通过中国人民银行分支机构查询授权机构名录进行验证。"}
{"id": 1157, "answer": ["C"]}
{"id": 1168, "answer": ["A", "C"]}
{"id": 1173, "answer": ["B"]}
{"id": 1167, "answer": "企业发行绿色债券时需规避的常见违规行为包括：（1）未按时完成存续期评估认证或未按要求整改评估结果；（2）评估认证机构未履行质量控制义务或存在执业质量问题；（3）未按规定公开披露评估认证信息；（4）未及时提交自查报告或整改情况；（5）选择不符合绿色债券支持目录的项目。这些行为可能导致绿色债券标识被撤销或面临监管处罚。"}
{"id": 1171, "answer": "银行应从以下方面完善房地产授信管理体系：（1）建立与风险承受能力相适应的授信管理体制，结合宏观经济分析和压力测试动态调整策略；（2）严格执行贷款政策，强化借款人资质审核，确保还款能力；（3）加强房地产价格、信贷资产质量的监测，落实分区域、分业态风险分析及“名单制”管理；（4）优化内控机制和业绩考核体系，提升分支机构风险意识；（5）配合监管要求，落实宏观调控政策并接受监管检查，防范跨区域授信风险。"}
{"id": 1174, "answer": ["C"]}
{"id": 1178, "answer": ["C"]}
{"id": 1162, "answer": "2010年签订的利率互换合同的法律效力状态需满足以下条件：1. 合同内容符合《中国人民银行关于开展人民币利率互换业务有关事宜的通知》（银发200818号）中对利率互换的定义（即约定未来利息交换的金融合约）；2. 合同以书面形式签订（包括成交单、合同书、数据电文等）；3. 若未通过交易中心交易系统，需按第六条要求完成备案（备案为监管要求，不影响合同效力本身）。若上述条件均满足，则合同具有法律效力；若存在未书面化或未符合定义的情形，则可能效力瑕疵。"}
{"id": 1179, "answer": "小额支付系统质押业务的两种核心管理类别是质押品管理业务和质押额度管理业务。"}
{"id": 1175, "answer": ["B", "D"]}
{"id": 1176, "answer": ["C", "D"]}
{"id": 1181, "answer": "储蓄国债（凭证式）收款凭证遗失后，投资者应立即到原购买承销团成员营业网点办理挂失手续。承销团成员审核后需及时补制新凭证，不得收取手续费。补制流程需提供投资者身份证明，若委托他人代办还需提供代办人证件。"}
{"id": 1182, "answer": ["C"]}
{"id": 1184, "answer": ["B"]}
{"id": 1166, "answer": ["A"]}
{"id": 1177, "answer": ["A", "B"]}
{"id": 1180, "answer": ["A", "B"]}
{"id": 1185, "answer": ["C"]}
{"id": 1187, "answer": ["B", "C", "D"]}
{"id": 1189, "answer": "首次报送明细类数据时需补充2018年1月1日以来发生的交易记录。"}
{"id": 1191, "answer": ["A", "B", "D"]}
{"id": 1183, "answer": "应从以下方面核查合法性：1. 核查交易是否符合大额交易报告标准（如跨境款项划转金额是否超过规定阈值）；2. 检查账户是否存在频繁交易、构造性交易或规避限额的行为；3. 关注账户余额与交易额比例、交易笔数异常及跨行转账情况；4. 评估跨境交易的地域风险，审查账户是否涉及境外IP地址或MAC地址；5. 确认机构账户交易是否与经营范围、规模相符，是否存在关联企业异常往来；6. 检查账户操作是否涉及构造性资金流动或短期集中开户、资金集中转出等异常行为。"}
{"id": 1193, "answer": ["B"]}
{"id": 1192, "answer": "货币经纪公司应向金融基础设施和金融信息服务商收取数据服务费用。第一类情形是金融信息服务商将数据用于商业用途（如行情展示、增值服务）时，货币经纪公司可按商业化原则收取费用；第二类情形是金融基础设施在履行其职能过程中使用数据时，货币经纪公司可根据数据类型、处理成本等因素收取费用。"}
{"id": 1188, "answer": "应从以下层面系统性整改：1. **人力资源层面**，确保配备专业手语服务人员或具备手语能力的员工（依据段落1、段落4）；2. **员工培训层面**，定期开展无障碍服务技能培训，提升员工服务能力（段落1）；3. **服务流程层面**，优化服务流程，确保聋哑客户在办理业务时可获得手语翻译支持（段落2）；4. **制度建设层面**，制定残疾人客户服务标准，明确责任部门并强化监督（段落5）；5. **管理层责任层面**，落实整改问责机制，确保整改措施有效执行（段落5）。"}
{"id": 1190, "answer": ["C"]}
{"id": 1170, "answer": []}
{"id": 1194, "answer": ["A", "B"]}
{"id": 1196, "answer": ["B"]}
{"id": 1195, "answer": "申请小微企业无还本续贷需满足以下基本条件：1. 贷款到期后仍有融资需求且临时存在资金困难；2. 企业具备良好的信用记录和还款能力（需通过第一还款来源审核）；3. 符合国家产业政策导向（如创新驱动、环保等）；4. 银行机构根据自身风险管控水平和信贷管理制度自主审批。具体条件可能因银行内部制度而异，但需确保符合监管政策要求。"}
{"id": 1202, "answer": ["A", "C"]}
{"id": 1201, "answer": ["A"]}
{"id": 1200, "answer": ["B"]}
{"id": 1198, "answer": ["C"]}
{"id": 1199, "answer": ["A"]}
{"id": 1186, "answer": ["D"]}
{"id": 1204, "answer": "商业银行不能自行决定扩大试点业务范围，相关调整需经银保监会或金融监管总局等监管机构审批。"}
{"id": 1207, "answer": ["A", "B", "C", "D"]}
{"id": 1203, "answer": ["C"]}
{"id": 1206, "answer": ["A", "D"]}
{"id": 1209, "answer": ["C"]}
{"id": 1208, "answer": ["B", "C"]}
{"id": 1210, "answer": ["B", "D"]}
{"id": 1211, "answer": ["C"]}
{"id": 1212, "answer": "商业银行未经持卡人激活信用卡时，不得扣收任何费用。但持卡人通过书面、客户服务电话录音、电子签名或双方认可的其他方式单独授权扣收的费用，以及换卡时已形成的债权债务关系除外。"}
{"id": 1197, "answer": []}
{"id": 1214, "answer": ["C"]}
{"id": 1215, "answer": ["B"]}
{"id": 1217, "answer": ["B"]}
{"id": 1213, "answer": ["C"]}
{"id": 1218, "answer": ["B", "C"]}
{"id": 1216, "answer": ["B"]}
{"id": 1222, "answer": ["B", "C"]}
{"id": 1221, "answer": ["C"]}
{"id": 1226, "answer": ["C"]}
{"id": 1225, "answer": ["B"]}
{"id": 1219, "answer": []}
{"id": 1224, "answer": ["A", "C"]}
{"id": 1227, "answer": ["B"]}
{"id": 1223, "answer": ["B"]}
{"id": 1229, "answer": ["C"]}
{"id": 1220, "answer": "合作银行办理外汇掉期业务需满足以下特殊准入条件：  \n1. 具备合作远期结售汇业务资格2年以上；  \n2. 近2年合作远期结售汇业务规模均达到即期结售汇业务规模的5%；  \n3. 上年度外汇资产季平均余额在等值2000万美元（含）以上；  \n4. 近2年外汇业务合规与审慎经营评估等级为B级（含）以上；  \n5. 具有完善的合作办理外汇衍生品业务管理制度。"}
{"id": 1205, "answer": ["A", "B", "D"]}
{"id": 1228, "answer": ["A"]}
{"id": 1232, "answer": "支付系统行号由12位定长数字组成，是参与者通过支付系统办理业务的身份识别代码。"}
{"id": 1231, "answer": ["B"]}
{"id": 1234, "answer": ["B"]}
{"id": 1230, "answer": ["B"]}
{"id": 1235, "answer": "根据现有检索段落，持港澳台居民居住证办理理财业务时，无需额外补充证明材料。居住证本身已作为合法身份证件，可直接用于办理银行、保险等金融业务。但需注意，若涉及《中国人民银行关于加强支付结算管理防范电信网络新型违法犯罪有关事项的通知》（银发〔2016〕261号）的额外验证要求，可能需进一步确认具体规定，但检索段落中未提供该文件的详细内容。"}
{"id": 1237, "answer": "金融机构在新规发布后需进行系统性自查的方面包括：1. 全面覆盖体制、机制、系统、流程、人员及业务（段落1）；2. 识别并评估系统性风险隐患（如业务规模、投资者情况等），并形成风险监管报告（段落3、段落4）；3. 对存量业务进行合规整改，确保符合新规要求（段落2）。"}
{"id": 1242, "answer": "不能。根据中国银保监会规定，保险资金参与信用风险缓释工具和信用保护工具业务仅限于对冲风险，不得作为信用风险承担方（段落2）。这意味着保险资金通过此类工具管理风险的目的是转移或分散已有风险，而非主动承担新增风险。"}
{"id": 1243, "answer": ["A", "D"]}
{"id": 1240, "answer": ["C"]}
{"id": 1241, "answer": "银行卡清算机构的高级管理人员需满足以下基本条件：1. 具备相应的任职专业知识；2. 有5年以上银行、支付或清算从业经验；3. 具有良好的品行和声誉；4. 担任职务所需的独立性；5. 无重大过失或犯罪记录，且未因违法行为被金融监管机构取消任职资格（未逾5年）；6. 需提交学历、技术职称、独立性说明及无犯罪记录等证明材料。"}
{"id": 1239, "answer": ["B"]}
{"id": 1246, "answer": ["B", "C"]}
{"id": 1247, "answer": ["A"]}
{"id": 1236, "answer": ["D"]}
{"id": 1244, "answer": ["C"]}
{"id": 1245, "answer": "财务公司应采取以下合规措施：1. 建立并维护覆盖各业务领域的信息管理系统，持续监控流动性、操作等风险（段落2）；2. 加强股东和关联交易管理，定期评估股东资质并及时报告违规行为（段落2）；3. 制定恢复和处置计划，明确风险应对策略（段落1第四十七条）；4. 对异常风险指标及时向银保监会派出机构报告，并配合整改要求（段落4）；5. 在必要时主动调整业务规模或暂停高风险业务，接受监管机构的监管措施（段落4）。"}
{"id": 1248, "answer": ["A", "C"]}
{"id": 1249, "answer": ["A", "B", "C", "D"]}
{"id": 1250, "answer": ["A", "B"]}
{"id": 1233, "answer": ["A", "C"]}
{"id": 1255, "answer": ["B", "C"]}
{"id": 1252, "answer": ["C"]}
{"id": 1251, "answer": "用户需通过绑定账户转入资金验证，并经本人同意后，银行可为其Ⅲ类户开通非绑定账户入金功能，从而实现他行转账。具体操作包括：1. 通过绑定账户（如Ⅰ类户）向Ⅲ类户转入资金以激活账户；2. 确认身份后，银行根据规定调整限额，允许接收非绑定账户的小额转入资金（日累计2000元，年累计5万元）。若未绑定账户，可通过银行面对面核实身份开立Ⅲ类户，以获得相应功能。"}
{"id": 1253, "answer": ["A", "D"]}
{"id": 1256, "answer": ["B"]}
{"id": 1257, "answer": ["B"]}
{"id": 1258, "answer": "银行卡境外交易商户类别码的控制原则包括：1）严格限定商户类别码范围，禁止用于证券投资、房地产交易及博彩等非法交易；2）发卡银行需在系统中对禁止类交易直接拒绝、对限制类交易实施单笔金额限制；3）中国银联需对境外特约商户类别码进行严格控制和管理；4）境外收单机构须规范设置商户类别码等信息，并接受动态监控与风险检查；5）违规设置或使用商户类别码的机构将面临违约责任追究或取消收单资格。"}
{"id": 1260, "answer": ["B"]}
{"id": 1259, "answer": ["B"]}
{"id": 1264, "answer": ["B", "C", "D"]}
{"id": 1261, "answer": "试点理财公司需建立配套机制包括：1. 试点工作领导机制及制度建设，明确职责并保障资源投入；2. 与养老理财相适应的治理架构、管理模式、投研能力及考核体系；3. 健全风险管理机制，实施第三方独立托管，探索跨周期投资模式；4. 规范产品设计、销售管理、信息披露及投资者保护；5. 定期向监管部门报送进展，配合政策宣传引导，培育投资者长期价值投资理念；6. 产品登记与合规管理，确保审慎合规展业。"}
{"id": 1268, "answer": ["B", "D"]}
{"id": 1267, "answer": ["B"]}
{"id": 1266, "answer": ["B"]}
{"id": 1265, "answer": ["C"]}
{"id": 1269, "answer": ["B"]}
{"id": 1238, "answer": ["C"]}
{"id": 1270, "answer": ["C"]}
{"id": 1262, "answer": ["B"]}
{"id": 1276, "answer": ["B"]}
{"id": 1273, "answer": ["B"]}
{"id": 1277, "answer": ["B"]}
{"id": 1272, "answer": ["B"]}
{"id": 1274, "answer": "批量开户（或批量迁移）需提交的核心材料包括：核准类银行结算账户的开户许可证正本或开户许可证遗失证明、单位银行结算账户批量迁移申请表、单位银行结算账户批量迁移数据文件。"}
{"id": 1254, "answer": ["B"]}
{"id": 1271, "answer": ["C"]}
{"id": 1279, "answer": ["B"]}
{"id": 1280, "answer": ["A", "B", "C", "D"]}
{"id": 1275, "answer": ["A", "C"]}
{"id": 1282, "answer": "当衍生品交易规模突破监管阈值时，应立即停止新增高杠杆业务（如无限风险产品、再衍生产品），并在过渡期内完成规模调整，包括平盘或终止存续交易。同时需与监管部门沟通并书面咨询意见，确保符合监管要求。"}
{"id": 1289, "answer": ["B"]}
{"id": 1288, "answer": ["B"]}
{"id": 1287, "answer": ["C"]}
{"id": 1284, "answer": ["D"]}
{"id": 1283, "answer": "发现特约商户疑似洗钱时，应立即采取以下紧急措施：1. 阻断可疑交易并联系客户核实交易真实性（段落2第四十二条）；2. 对特约商户实施延迟资金结算、暂停交易或冻结账户等限制性措施（段落3第四十三条）；3. 若发现涉嫌违法犯罪活动，需及时向公安机关报案（段落3第四十三条）。同时，应通过风险监测体系持续追踪异常交易（段落2第四十二条），并确保相关操作符合反洗钱法规要求。"}
{"id": 1285, "answer": ["A", "B"]}
{"id": 1290, "answer": ["B"]}
{"id": 1281, "answer": ["B"]}
{"id": 1278, "answer": ["A", "B"]}
{"id": 1293, "answer": ["C"]}
{"id": 1263, "answer": ["B"]}
{"id": 1297, "answer": ["B"]}
{"id": 1298, "answer": ["C"]}
{"id": 1292, "answer": ["A", "B"]}
{"id": 1291, "answer": "结算代理人履行日常监督职责时需重点关注以下事项：1. 对委托人身份、授权及经营范围等进行真实性审查；2. 建立业务人员定期轮岗制度，实现自营与代理业务分离；3. 对委托人开展业务培训并充分提示风险；4. 定期自查业务开展情况、流程制度及岗位设置，并提交经法人代表签字的自查报告；5. 审查资金收付的真实性与合规性，履行反洗钱和反恐怖融资义务。这些要求主要依据段落1、2和4中的相关规定。"}
{"id": 1295, "answer": "保险保障基金的主要用途包括：1）通过投资银行存款、政府债券等实现保值增值；2）在保险公司出现偿付能力问题或重大风险时，用于救助以维护保险业稳定。"}
{"id": 1299, "answer": ["A", "B"]}
{"id": 1296, "answer": "加强新市民金融消费者权益保护需采取以下措施：1. 完善金融知识普及，通过官网、APP等设立教育专区，开展防骗反诈宣传（段落1）；2. 畅通投诉渠道，建立多元化纠纷解决机制，如第三方调解中心（段落5）；3. 推动信息共享，整合政务数据优化信用评价体系（段落3）；4. 强化金融机构主体责任，设立消保委员会并规范合作机构管理（段落4）；5. 加强组织协同，推动地方政府与银保监会协作落实政策（段落2）。"}
{"id": 1300, "answer": ["B"]}
{"id": 1294, "answer": ["A", "D"]}
{"id": 1301, "answer": ["C"]}
{"id": 1303, "answer": ["D"]}
{"id": 1306, "answer": ["B"]}
{"id": 1305, "answer": ["A", "C"]}
{"id": 1302, "answer": "保险资管产品参与证券出借面临以下特殊限制：1. 借入人需满足净资产和评级要求（证券公司净资产≥60亿且评级≥A类，商业银行净资产≥100亿）；2. 管理人需为符合条件的证券公司、证券资管公司或基金公司；3. 保险资管公司监管评级不低于C类；4. 需履行尽职调查、风险管理等主动管理责任；5. 证券出借需纳入托管范围并签订托管合同；6. 严格关联交易管理，禁止利益输送；7. 定期向银保监会报告证券出借情况及风险事件。"}
{"id": 1310, "answer": ["C"]}
{"id": 1311, "answer": "半年的保费交纳基数计算方法为：将投保机构在该半年内每月末的被保险存款余额相加，再除以6，即每6个月保费交纳基数=∑各月末被保险存款余额/6。此方法依据段落1第四条的规定。"}
{"id": 1286, "answer": ["A", "B", "D"]}
{"id": 1315, "answer": ["C"]}
{"id": 1316, "answer": ["B"]}
{"id": 1304, "answer": ["B", "C"]}
{"id": 1319, "answer": ["B", "C"]}
{"id": 1314, "answer": ["C", "D"]}
{"id": 1317, "answer": ["B", "C"]}
{"id": 1320, "answer": ["C"]}
{"id": 1307, "answer": []}
{"id": 1321, "answer": ["B", "C"]}
{"id": 1323, "answer": ["A"]}
{"id": 1308, "answer": ["B"]}
{"id": 1312, "answer": ["C", "D"]}
{"id": 1318, "answer": ["C", "D"]}
{"id": 1327, "answer": ["C"]}
{"id": 1326, "answer": ["B"]}
{"id": 1329, "answer": "大额存单的标准化期限包括1个月、3个月、6个月、9个月、1年、18个月、2年、3年和5年，共9个种类。"}
{"id": 1325, "answer": ["A", "C"]}
{"id": 1324, "answer": ["A", "C", "D"]}
{"id": 1331, "answer": ["B", "C"]}
{"id": 1330, "answer": ["B"]}
{"id": 1328, "answer": ["B"]}
{"id": 1332, "answer": "客户通过互联网渠道开立存款账户时需履行的基本义务包括：1. 提供真实、完整的信息，配合银行进行身份验证（如留存核实记录，确保信息准确）；2. 遵守相关法律法规及监管规定，不得通过互联网渠道规避监管要求；3. 保护个人信息安全，避免泄露；4. 配合银行的风控管理，如实告知账户用途，不得参与违规操作。这些义务基于《商业银行法》《储蓄管理条例》及《关于规范商业银行通过互联网开展个人存款业务的通知》（银保监办发〔2021〕9号）等规定。"}
{"id": 1313, "answer": ["C"]}
{"id": 1335, "answer": "根据段落1第22条，回购到期应解除质押关系。若一方未能按期归还资金构成违约，守约方有权依据合同约定及法律规定，通过司法途径或协商处理质押债券以实现债权，具体操作需结合合同条款和相关法律法规执行。"}
{"id": 1334, "answer": "经纪商通过分阶段信息披露（如交易前核对必要信息、交易后按协议处理）、严格保密管理（如限制信息访问权限、总部与分支机构信息隔离）以及技术手段（如集中清算切断原始交易对手关系）平衡信息披露义务与商业秘密保护，确保合规性与风险可控。"}
{"id": 1336, "answer": ["B"]}
{"id": 1337, "answer": "当广州遭遇红色台风警报时，当天的支票交易流程将暂停票据交换，并顺延上一工作日提出票据的资金抵用时间。需由广州银行电子结算中心、深圳金融电子结算中心通知粤港两地金融主管机关和粤方银行；同时，香港银行同业结算有限公司需通知粤港两地金融主管机关和香港银行。"}
{"id": 1338, "answer": "保险机构应持续监测担保物价值变动，当担保物贬值导致实际担保比例低于合同约定的102%时，要求借入人补足担保物；若借入人违约，保险机构有权根据法律规定和合同约定处置担保物以满足索赔需要。"}
{"id": 1340, "answer": ["D"]}
{"id": 1341, "answer": ["C"]}
{"id": 1322, "answer": ["B", "D"]}
{"id": 1343, "answer": ["D"]}
{"id": 1342, "answer": ["A", "C"]}
{"id": 1344, "answer": "备案成功后可以进行的操作包括：1. 持主管国税机关盖章的《备案表》到外汇指定银行办理付汇审核手续（根据段落2）；2. 开展跨境资金集中运营业务，如外债额度集中、境外放款额度集中、经常项目资金集中收付等（根据段落3）。"}
{"id": 1346, "answer": ["A", "C"]}
{"id": 1345, "answer": "根据中国人民银行银办发〔2016〕15号通知，境外机构（含港澳）在中国境内银行开立的人民币账户资金可转存为定期存款。因此，若港澳汇回的未使用人民币属于境外机构账户资金（如企业或机构账户），可申请转存定期。但若为个人账户，需进一步确认是否适用该政策。"}
{"id": 1333, "answer": ["A", "B"]}
{"id": 1309, "answer": ["B", "D"]}
{"id": 1351, "answer": "财务公司发行债券的资金用途需符合国家产业政策和相关政策规定，用于支持集团主业发展和配置中长期资产，解决资产负债期限不匹配问题，且不得用于与集团和财务公司主业无关的风险性投资。"}
{"id": 1352, "answer": ["B"]}
{"id": 1347, "answer": []}
{"id": 1350, "answer": "金融机构处理客户提交的半额兑换特殊残缺人民币时，需核对人民银行转来的专用袋、鉴定书及持有人出示的鉴定书，确认无误后凭鉴定结论填制《金融机构特殊残缺污损人民币兑换单》。半额兑换的人民币归入能整除兑换金额的现行人民币最大面额券别，并与全额兑换的残缺人民币一并交存至人民银行发行库。兑换过程中需分券别按半额使用专用袋密封，兑换单一式三联（金融机构留存、粘贴于专用袋、交持有人），确保兑换标准符合《中国人民银行残缺污损人民币兑换办法》要求。"}
{"id": 1339, "answer": ["B"]}
{"id": 1353, "answer": ["A", "C"]}
{"id": 1359, "answer": ["C"]}
{"id": 1356, "answer": "持卡人需携带新的有效身份证件、发证机关出具的证明文件及军人保障卡，到发卡银行当地营业网点办理变更手续。若涉及支付机构，需在身份证件过期前更新信息，或在变更时重新识别身份。"}
{"id": 1355, "answer": ["D"]}
{"id": 1361, "answer": ["B"]}
{"id": 1348, "answer": ["B", "D"]}
{"id": 1357, "answer": ["A", "C"]}
{"id": 1358, "answer": "质押式回购与买断式回购的核心区别在于交易结构与权利义务：质押式回购中正回购方将票据作为质押物融入资金，回购期间票据所有权仍归正回购方，且质押金额不得超过票据面额，到期需解除质押；买断式回购则是正回购方将票据卖给逆回购方，回购期间票据所有权转移至逆回购方，到期以约定价格买回票据，且无金额上限约束。"}
{"id": 1360, "answer": ["B"]}
{"id": 1362, "answer": ["C"]}
{"id": 1366, "answer": ["C"]}
{"id": 1364, "answer": "银行应立即收回被挪用的贷款，加强贷后资金监控并实施重点监测，将违规企业信息载入征信管理系统，同时向其他商业银行通报其违规行为，并依法严肃处理相关责任人。"}
{"id": 1354, "answer": ["A", "D"]}
{"id": 1369, "answer": ["D"]}
{"id": 1371, "answer": ["B"]}
{"id": 1363, "answer": "保险机构在已投资的金融产品发生重大违约时，应采取以下措施：1. 根据审慎原则及时计提减值准备，真实反映资产价值（段落1、段落2）；2. 调整投资限额、风险限额和止损限额，维护资产安全（段落1、段落2）；3. 持续跟踪产品管理运作，定期评估风险并采取有效措施管理相关风险（段落1）；4. 向银保监会按规定报告违约情况（段落1、段落2）。"}
{"id": 1365, "answer": ["B"]}
{"id": 1370, "answer": ["B"]}
{"id": 1367, "answer": "开办机构需采取以下风控手段：1. 确保足额质押并持续监控质押券价值（段落1、段落4）；2. 建立风险控制机制（段落1）；3. 制定投资者适当性管理制度，匹配投资者风险承受能力（段落2）；4. 加强内控管理和系统建设，实现交易服务全程留痕（段落2）；5. 签署主协议并严格履行回购合同条款，包括禁止动用质押债券、限制回购期限（段落5）。"}
{"id": 1372, "answer": ["C"]}
{"id": 1376, "answer": ["C"]}
{"id": 1368, "answer": ["B"]}
{"id": 1373, "answer": ["B"]}
{"id": 1378, "answer": []}
{"id": 1381, "answer": ["B"]}
{"id": 1379, "answer": ["A"]}
{"id": 1380, "answer": ["C"]}
{"id": 1375, "answer": ["C"]}
{"id": 1383, "answer": ["C"]}
{"id": 1385, "answer": ["C"]}
{"id": 1386, "answer": ["C"]}
{"id": 1349, "answer": ["B"]}
{"id": 1387, "answer": ["A", "B"]}
{"id": 1374, "answer": ["A", "C"]}
{"id": 1382, "answer": ["A", "C"]}
{"id": 1388, "answer": ["B"]}
{"id": 1393, "answer": ["A"]}
{"id": 1394, "answer": ["C"]}
{"id": 1389, "answer": ["C"]}
{"id": 1396, "answer": ["C"]}
{"id": 1390, "answer": ["A", "C"]}
{"id": 1391, "answer": ["A"]}
{"id": 1395, "answer": "国企的全资子公司作为备案主体，需根据其公司类型确定受益所有人。若为国有独资公司，法定代表人即为受益所有人，需在设立登记时或30日内通过登记注册系统备案。若存在其他符合条件的自然人（如持股25%以上或实际控制权），则需按标准1、标准2或标准3进行备案。备案信息需及时更新，并由地方市场监管部门督促完成。"}
{"id": 1397, "answer": ["C"]}
{"id": 1398, "answer": ["C"]}
{"id": 1401, "answer": ["D"]}
{"id": 1402, "answer": "小微企业划型的法定依据是《关于印发中小企业划型标准规定的通知》（工信部联企业〔2011〕300号）。"}
{"id": 1403, "answer": ["B"]}
{"id": 1400, "answer": ["B"]}
{"id": 1404, "answer": "境外银行类机构投资者参与银行间外汇市场可采取以下接入方式：1. 作为客户与托管人、结算代理人或境内其他金融机构直接交易；2. 申请成为中国外汇交易中心会员直接进入银行间外汇市场交易；3. 申请成为外汇交易中心会员通过主经纪业务进入银行间外汇市场交易。"}
{"id": 1399, "answer": ["B", "C"]}
{"id": 1406, "answer": ["A", "C"]}
{"id": 1405, "answer": "完整的稽核工作程序需经历准备、实施、报告、处理、建档五个阶段。准备阶段：制定稽核方案，明确检查目标与重点；实施阶段：通过谈话、核对资料等方式开展检查并形成初步结论；报告阶段：撰写包含问题分析与整改建议的《稽核报告》；处理阶段：对违规责任人提出处罚意见并执行；建档阶段：归档稽核资料以备后续查阅。"}
{"id": 1407, "answer": ["B"]}
{"id": 1384, "answer": ["A"]}
{"id": 1377, "answer": ["A", "C", "D"]}
{"id": 1408, "answer": ["B"]}
{"id": 1412, "answer": ["C"]}
{"id": 1409, "answer": ["A", "D"]}
{"id": 1411, "answer": ["B"]}
{"id": 1418, "answer": ["B"]}
{"id": 1417, "answer": ["C"]}
{"id": 1410, "answer": "境外机构投资者需准备中国注册会计师出具的投资收益专项审计报告和税务备案表（按规定无需提供的除外），并提交书面申请或指令，由托管人办理资金汇出手续。"}
{"id": 1414, "answer": ["A", "B", "D"]}
{"id": 1419, "answer": ["C"]}
{"id": 1416, "answer": ["C"]}
{"id": 1413, "answer": "发现银行卡被盗刷后，应立即联系发卡银行挂失卡片并冻结账户，及时报警备案，配合银行调查并提供相关交易信息，同时监控账户动态，必要时申请补办新卡。银行将根据流程采取账户锁定、上报监管机构等措施以防止损失扩大。"}
{"id": 1421, "answer": ["A", "C"]}
{"id": 1420, "answer": "商业银行给小企业核定授信额度时需分析的基础报表包括企业财务报表（如资产负债表、利润表、现金流量表）、征信报告及信用评级数据，同时需评估其资产负债比例、偿债能力及信用等级（依据段落1、段落3）。"}
{"id": 1415, "answer": "债券交易流通机制改革后，各方机构的协同流程关键变化包括：1）信息传输方式由纸质转向电子化（段落1）；2）同业拆借中心需在1个工作日内完成服务准备，并集中保存交易数据（段落2、3、4）；3）登记托管结算机构需及时处理信息变更报告并监控投资者持股比例（段落3、4、5）；4）发行人需履行更严格的信息披露义务，包括重大事项公告（段落5）。这些调整提升了效率、透明度和市场规范性。"}
{"id": 1428, "answer": ["C"]}
{"id": 1431, "answer": ["B"]}
{"id": 1427, "answer": ["B"]}
{"id": 1422, "answer": "申请成为小微商户需提供主要证明材料包括：商户主要负责人身份证明文件，以及辅助证明材料（如营业场所租赁协议或产权证明、集中经营场所管理方出具的证明文件等），以证明其真实、合法从事商品或服务交易活动。"}
{"id": 1425, "answer": "债权人主张将公证费用纳入执行范围的前提是公证债权文书中明确约定由债务人承担该费用，并且有明确的数额或计算方法。"}
{"id": 1423, "answer": "教育储蓄利息所得税的适用条件包括：储户为符合规定的在校学生、按零存整取方式开户、存期内未中断且提供有效“证明”文件。豁免情形为：储户能提供“证明”时，无论提前支取或到期支取均免征利息所得税；若无法提供“证明”或因户口迁移等特殊情况无法提供，则需按活期利率计息并征收利息所得税（段落1、段落2、段落3）。"}
{"id": 1424, "answer": "债券收益率曲线编制的核心要求包括：基于全面、客观、合理的债券数据源并剔除异常价格影响；选取科学可靠的构造模型以适应市场多变形态，确保光滑性和稳定性；充分反映真实收益率水平；具备科学性、可比性、可校验性和可回溯性；同时需考虑债券条款、发行人信用状况及市场流动性等因素。"}
{"id": 1430, "answer": ["B"]}
{"id": 1392, "answer": ["A", "B", "D"]}
{"id": 1433, "answer": ["C"]}
{"id": 1429, "answer": "银行资本补充债券发行人需满足的基本资质包括：资本充足率符合监管规定；提交最近三年经审计的财务会计报告；提供信用评级机构出具的金融债券信用评级报告；董事会决议及偿债计划专项报告；以及满足信息披露要求（如定期报告和重大事件披露）。"}
{"id": 1432, "answer": ["B"]}
{"id": 1437, "answer": ["A", "D"]}
{"id": 1435, "answer": ["B"]}
{"id": 1439, "answer": ["C"]}
{"id": 1436, "answer": []}
{"id": 1441, "answer": ["B", "D"]}
{"id": 1445, "answer": ["B"]}
{"id": 1440, "answer": ["C"]}
{"id": 1434, "answer": ["B", "D"]}
{"id": 1438, "answer": "发现无障碍厕所故障应采取以下应急措施：1. 立即记录故障现象并向上级报告，必要时电话通报；2. 联系专业维护人员或技术支持团队进行排查与修复；3. 启动应急预案，协调资源确保设施尽快恢复使用；4. 故障排除后进行状态核对，确保功能正常；5. 按规定提交书面报告，留存处理记录备查。"}
{"id": 1426, "answer": ["C"]}
{"id": 1444, "answer": ["B"]}
{"id": 1443, "answer": "根据现有检索内容，未明确提及增设自助存款机是否需要审批，但依据银行业监管常规，增设自助设备一般需经监管部门批准。因此，商业银行未经批准增设自助存款机可能涉及违规，需依据相关法规履行审批程序。"}
{"id": 1446, "answer": "不能。依据段落1，地方性法人商业银行（包括民营银行）通过互联网开展存款业务应服务其注册地客户，杭州民营银行无法接受北京客户的存款申请。"}
{"id": 1454, "answer": ["B"]}
{"id": 1451, "answer": ["A"]}
{"id": 1457, "answer": ["C"]}
{"id": 1450, "answer": ["B", "C"]}
{"id": 1453, "answer": ["B"]}
{"id": 1449, "answer": ["B"]}
{"id": 1442, "answer": ["A", "B"]}
{"id": 1456, "answer": "当国际外汇市场发生剧烈波动时，欧元的人民币汇率中间价通过人民币兑美元汇率中间价与上午9时国际外汇市场欧元兑美元汇率的套算机制同步更新。具体而言，中国外汇交易中心以当日人民币兑美元中间价为基准，结合欧元兑美元的实时市场汇率进行套算，从而动态调整欧元对人民币的中间价。"}
{"id": 1447, "answer": ["A"]}
{"id": 1462, "answer": ["B"]}
{"id": 1465, "answer": "付款人开户机构需在事先或者为付款人办理首笔代收业务时获取用户授权。"}
{"id": 1460, "answer": ["A", "C"]}
{"id": 1459, "answer": "监管部门建议通过优化工作流程（如调整业务准入、交易频率和金额限制）、加强内控制度建设、完善客户和业务风险监测机制（如高风险客户强化尽职调查、交易监测），以及调整资源配置优先级等措施重构流程，以防范虚假交易风险。"}
{"id": 1452, "answer": ["D"]}
{"id": 1455, "answer": "是的，会受到影响。因为2022年4月25日的存款准备金率调整针对未跨省经营的城市商业银行，且这类银行原本执行的存款准备金率高于5%（如段落2所述为6%），因此需下调0.25个百分点，导致其准备金率发生变化。"}
{"id": 1448, "answer": ["A", "C"]}
{"id": 1467, "answer": ["B"]}
{"id": 1466, "answer": "商家收到外币怀疑有问题时，首先应通过境内外币支付系统发起查询，要求相关方在1个工作日内查复（依据段落4）。若确认外币存在异常，可申请退汇并要求对方在1个工作日内答复（段落4）。若怀疑外币本身非法或伪造，需向省级以上公安、司法机关提交询证申请，相关部门将在10个工作日内书面答复（段落1）。同时，确保遵循支付系统规则，避免因违规操作引发处罚（段落2）。"}
{"id": 1458, "answer": []}
{"id": 1469, "answer": ["C"]}
{"id": 1463, "answer": ["A", "B"]}
{"id": 1468, "answer": ["B", "D"]}
{"id": 1472, "answer": "信托公司系统性影响评估的核心要素包括资产管理类信托资产规模（权重25%）、资产服务类信托资产规模（权重10%）、公益慈善类信托资产规模（权重5%）及同业负债余额等指标。权重分配逻辑基于各要素对金融体系稳健性的影响程度，通过量化指标分段赋分并加权汇总，最终评估总分用于判定是否具有系统性影响（85分以上为具有系统性影响）。"}
{"id": 1475, "answer": ["C"]}
{"id": 1471, "answer": ["A", "C"]}
{"id": 1470, "answer": ["B"]}
{"id": 1474, "answer": "对人民币合格投资者实施的宏观审慎管理机制，旨在防范系统性金融风险，通过动态调整监管政策维护跨境资金流动稳定。应参考的动态因素包括：跨境资金流动形势、离岸人民币市场流动性、人民币产品发展情况（段落4第四条），以及宏观经济形势（段落3第三条）。此外，还需关注金融体系韧性、市场波动性等系统性风险相关指标（段落5）。这些因素共同构成宏观审慎管理的决策依据。"}
{"id": 1478, "answer": ["B"]}
{"id": 1473, "answer": ["B"]}
{"id": 1479, "answer": ["C"]}
{"id": 1477, "answer": ["B"]}
{"id": 1480, "answer": ["B"]}
{"id": 1485, "answer": ["B"]}
{"id": 1483, "answer": ["C"]}
{"id": 1481, "answer": ["A"]}
{"id": 1464, "answer": ["B"]}
{"id": 1484, "answer": ["B", "C", "D"]}
{"id": 1486, "answer": ["C"]}
{"id": 1482, "answer": ["C"]}
{"id": 1476, "answer": ["C", "D"]}
{"id": 1492, "answer": ["B"]}
{"id": 1495, "answer": ["B"]}
{"id": 1493, "answer": ["B"]}
{"id": 1487, "answer": ["C"]}
{"id": 1490, "answer": ["B"]}
{"id": 1488, "answer": ["C"]}
{"id": 1461, "answer": ["A", "C", "D"]}
{"id": 1491, "answer": ["A", "B", "D"]}
{"id": 1496, "answer": ["C"]}
{"id": 1498, "answer": ["C"]}
{"id": 1499, "answer": ["A", "B", "C"]}
{"id": 1500, "answer": ["B"]}
{"id": 1497, "answer": ["A", "B", "D"]}
{"id": 1501, "answer": "社会组织因未获批准需撤销临时账户时，应取得民政部《关于注销临时存款账户的通知》（附件2）、拟任法定代表人身份证件，并提交所有捐资人签字或签章的退款申请，银行将按入资比例原路退回资金至捐资人账户。"}
{"id": 1489, "answer": ["B", "C"]}
{"id": 1504, "answer": ["C"]}
{"id": 1494, "answer": "保险机构投资债转股投资计划需满足以下条件：  \n1. 具备股权投资管理能力或股权投资计划产品管理能力（段落1）；  \n2. 投资范围限于市场化债转股资产、存款、标准化债权等（段落1、段落4）；  \n3. 单笔投资金额不得超过产品规模的50%，关联方合计不得超过80%（段落1、段落2）；  \n4. 市场化债转股资产不低于净资产的60%（段落4）；  \n5. 若份额分级，需为优先级份额（段落4）；  \n6. 按穿透原则分类管理，权益类资产比例≥80%时需纳入权益类资产比例管理（段落1、段落2）；  \n7. 发行人需公司治理良好且具备合规记录（段落4）。"}
{"id": 1508, "answer": ["C"]}
{"id": 1507, "answer": "检索段落中未明确提及参与联系机制的具体准入条件，因此无法直接提供答案。但根据监管机制的一般逻辑，参与机构可能需满足银监会规定的审慎性条件，如具备相关业务资质、合规能力及监管认可。建议参考银监会相关通知的完整内容以获取准确信息。"}
{"id": 1505, "answer": ["C", "D"]}
{"id": 1506, "answer": "已执行5％人民币存款准备金率的金融机构在2024年9月27日的调整中不会改变。"}
{"id": 1510, "answer": ["B"]}
{"id": 1502, "answer": "金融机构资管产品介入债券借贷业务时必须履行的特殊义务包括：（1）按照诚实信用、勤勉尽责的原则履行受托管理职责；（2）确保债权债务关系清晰，明确授权和责任承担机制；（3）严格履行信息披露义务；（4）确保履约保障品市值满足双方约定条件；（5）在标的债券付息时及时返还利息；（6）当融入余额超过规定比例时，需及时报告并说明原因。这些义务依据段落1、3、4的规定。"}
{"id": 1511, "answer": ["A", "C"]}
{"id": 1516, "answer": ["C"]}
{"id": 1512, "answer": ["C"]}
{"id": 1509, "answer": ["B"]}
{"id": 1514, "answer": ["A", "B"]}
{"id": 1517, "answer": ["B"]}
{"id": 1503, "answer": ["B"]}
{"id": 1515, "answer": ["A", "C"]}
{"id": 1521, "answer": ["B"]}
{"id": 1524, "answer": ["B", "C"]}
{"id": 1519, "answer": "投诉人委托他人代理征信投诉时，需额外准备以下文件：（1）代理人的有效身份证件或其他身份证明文件复印件；（2）授权委托书原件（需载明代理人姓名、代理事项、权限和期限，并由委托人签名或盖章）；若投诉人为法人或其他组织，还需提供法定代表人或主要负责人的授权委托书原件及法定代表人或主要负责人和经办人的有效身份证件复印件。"}
{"id": 1527, "answer": ["C"]}
{"id": 1518, "answer": ["B"]}
{"id": 1525, "answer": ["B"]}
{"id": 1520, "answer": "申请扶贫小额信用贷款的主要审核环节包括：1. 资格审查（确认是否为建档立卡贫困户并进行县乡村三级公告公示）；2. 信用评级（由村两委、驻村工作队协助开展贫困户信用评估）；3. 项目审核（乡级扶贫部门把关贷款项目合规性）；4. 贷款申请评估（银行机构对申请材料进行合规性审查）；5. 使用监督（中期跟踪贷款使用情况，确保资金用于生产发展）；6. 逾期贷款清收（后期落实贷款回收管理）。"}
{"id": 1526, "answer": ["A", "D"]}
{"id": 1523, "answer": ["A", "C", "D"]}
{"id": 1528, "answer": "印章停用后需先由印章管理部门进行封存；废止后应按规定上缴或销毁，销毁时须实行双人监销并全程录像留档。"}
{"id": 1513, "answer": ["A"]}
{"id": 1530, "answer": ["B"]}
{"id": 1522, "answer": "商业银行应通过动态监测集团客户的经营和财务状况，建立风险预警机制，及时识别影响履约能力的重大事项（如财务恶化、抵押物变化等），并采取调整授信额度、风险分类及风险处置措施。具体包括：1）定期评估客户整体信用状况；2）对重大风险事件进行实地调查与记录；3）根据监测结果动态调整授信策略，如缩减授信或要求提前还款；4）制定统一授信管理制度，防范关联交易带来的风险转移。这些措施依据《商业银行集团客户授信业务风险管理指引》和《商业银行小企业授信工作尽职指引》中的相关规定。"}
{"id": 1531, "answer": ["C"]}
{"id": 1536, "answer": ["C"]}
{"id": 1529, "answer": ["B"]}
{"id": 1539, "answer": ["B"]}
{"id": 1535, "answer": "城市商业银行需通过中国人民银行所在地分行或营业管理部提交月度外币利率数据，由其汇总后转报中国人民银行总行。"}
{"id": 1540, "answer": ["B"]}
{"id": 1532, "answer": ["B", "C"]}
{"id": 1534, "answer": "发现白条抵库现象后，应立即停止违规行为，全面核对账务确保账账、账款、账实相符（依据段落2、3），完善金库尾箱管理制度并严格执行查库制度（如每周、每季、每年检查）（段落3），加强视频监控等技防措施（段落2），由首席合规官组织整改并报告董事会或高管（段落4），同时接受监管机构的督查与处罚（段落1）。"}
{"id": 1538, "answer": ["B"]}
{"id": 1541, "answer": ["D"]}
{"id": 1543, "answer": ["C"]}
{"id": 1537, "answer": ["A", "C"]}
{"id": 1542, "answer": ["B"]}
{"id": 1546, "answer": ["D"]}
{"id": 1533, "answer": ["B"]}
{"id": 1544, "answer": ["A", "C"]}
{"id": 1548, "answer": ["A", "C"]}
{"id": 1547, "answer": ["C"]}
{"id": 1551, "answer": ["C"]}
{"id": 1552, "answer": ["D"]}
{"id": 1549, "answer": ["B", "C"]}
{"id": 1550, "answer": []}
{"id": 1559, "answer": ["B"]}
{"id": 1553, "answer": ["A"]}
{"id": 1560, "answer": "信贷资产证券化发起机构在风险自留方面可以采取的两种主要方式是：（1）持有由其发起的证券化产品的一定比例（不低于发行规模的5%）；（2）持有最低档次资产支持证券的比例（不低于该档次发行规模的5%）。"}
{"id": 1558, "answer": ["B"]}
{"id": 1561, "answer": "商业保理企业若存在重大待决诉讼，须在事项发生后10个工作日内向金融监管局报告。"}
{"id": 1555, "answer": ["C"]}
{"id": 1554, "answer": ["A", "B", "C", "D"]}
{"id": 1556, "answer": ["A", "B"]}
{"id": 1563, "answer": "银联国际在境外清算资金购汇时，若从境内发卡机构收取人民币，需在境内清算代理行统一办理购汇，将人民币兑换为外币后支付给境外收单机构。同时，可根据业务需求提前购买备付金汇往境外清算代理行账户，以满足特定时期的清算需求。"}
{"id": 1565, "answer": ["A", "C"]}
{"id": 1569, "answer": "10个工作日。"}
{"id": 1568, "answer": "发现银行卡可能存在盗刷风险时，应立即联系发卡银行挂失卡片并冻结账户，同时向公安机关报案。根据段落1所述，银行需加强信息安全防护（如禁止明文存储客户密码、磁道数据），若发现异常交易，应要求银行核查并采取技术手段防范伪卡复制等风险。此外，需监控账户动态，及时报告可疑交易。"}
{"id": 1566, "answer": ["B"]}
{"id": 1564, "answer": "联合授信对机械制造企业融资的利弊如下：  \n**利**：1. **风险控制与效率提升**：通过信息共享机制，多家银行可共同评估企业信用，降低过度授信风险，同时提高融资效率（段落1、段落5）。2. **更精准的授信额度**：联合授信委员会综合企业资产负债、现金流、行业等因素测算额度，可能提供更合理的融资支持（段落3、段落4）。  \n**弊**：1. **融资灵活性受限**：银行需协调统一授信条件，可能限制企业与单一银行的谈判空间，增加融资成本（段落4）。2. **合规压力增加**：企业需披露更多信息并满足联合授信的适用条件（如融资余额达标），可能对中小企业形成门槛（段落2）。3. **潜在融资限制**：若企业融资余额未达到联合授信标准，可能无法享受该机制，导致融资渠道受限（段落2）。"}
{"id": 1567, "answer": ["C"]}
{"id": 1572, "answer": ["C"]}
{"id": 1557, "answer": []}
{"id": 1573, "answer": ["B"]}
{"id": 1577, "answer": "金融机构应对新客户的风险评级在建立业务关系后的10个工作日内完成。"}
{"id": 1578, "answer": ["A", "B", "C", "D"]}
{"id": 1545, "answer": []}
{"id": 1574, "answer": ["B"]}
{"id": 1576, "answer": "机构应制定针对市场中断、系统故障等极端情形的应急处置方案，及时披露中断原因并尽快恢复；建立主备岗机制与人员定期互换，储备应急设备和物资，确保技术预警与通讯保障；通过电子化、线上化方式维持服务连续性，并优化咨询与投诉流程，确保服务不中断。"}
{"id": 1582, "answer": ["B"]}
{"id": 1571, "answer": ["B"]}
{"id": 1583, "answer": ["B", "C"]}
{"id": 1581, "answer": ["C"]}
{"id": 1575, "answer": ["A"]}
{"id": 1579, "answer": ["A", "D"]}
{"id": 1580, "answer": ["B"]}
{"id": 1585, "answer": "套期保值类业务需符合套期会计规定，用于对冲特定风险，划入银行账户管理，并可享受风险缓释；非套期保值类业务包括除套期保值外的所有交易，划入交易账户管理，需计提市场风险资本且受风险暴露上限约束。界定依据为是否符合套期会计、风险对冲目的及资本监管要求。"}
{"id": 1587, "answer": ["C"]}
{"id": 1590, "answer": ["B"]}
{"id": 1588, "answer": ["A", "C"]}
{"id": 1589, "answer": ["A", "B"]}
{"id": 1586, "answer": ["C"]}
{"id": 1592, "answer": ["A", "C"]}
{"id": 1570, "answer": ["C"]}
{"id": 1595, "answer": ["C"]}
{"id": 1591, "answer": "科创型轻资产企业申请信用贷款时需具备的核心资质包括：符合国家产业政策及科技领域要求（如属于国家重点支持的高新技术领域）、信用良好、创始人具备专业专注能力且拥有知识产权、财务稳健并具备稳定还款来源（如现金流或订单保障），同时可依托知识产权等动产质押降低对抵押物的依赖（段落2、4、5）。"}
{"id": 1594, "answer": ["C"]}
{"id": 1597, "answer": ["B"]}
{"id": 1598, "answer": ["A", "C"]}
{"id": 1562, "answer": ["A"]}
{"id": 1596, "answer": "根据监管要求，商业银行应立即采取以下措施：1. 要求客户提前还款或缩减授信额度；2. 将授信划入问题授信并指定专人管理；3. 重新审核授信文件，确认实际授信余额；4. 上报银监会批准后实施处置（如终止授信）。同时，需依据段落4第三十五条，不得继续支持违规用途的授信。"}
{"id": 1601, "answer": ["B"]}
{"id": 1599, "answer": ["C"]}
{"id": 1603, "answer": ["A", "B", "D"]}
{"id": 1600, "answer": ["D"]}
{"id": 1602, "answer": "银行应首先检查是否已完成阅读机具的软件升级，若未升级需联系机具生产企业进行技术调整；同时可采取人工识别方式处理；此外，需加强员工培训，确保能熟练操作新版居住证的识别流程。"}
{"id": 1606, "answer": ["A", "C"]}
{"id": 1593, "answer": ["B", "D"]}
{"id": 1607, "answer": "电子商业汇票系统危机处置中数据恢复的两阶段核心任务分别是：第一阶段恢复故障发生日以前的数据（通过备份数据）及处理当日丢失数据（根据系统状态分情况处理）；第二阶段完成系统状态调整、基础数据验证后恢复系统运行并重启电子商业汇票业务。"}
{"id": 1610, "answer": ["C"]}
{"id": 1609, "answer": ["A", "B", "D"]}
{"id": 1604, "answer": ["D"]}
{"id": 1605, "answer": ["A", "B", "C", "D"]}
{"id": 1611, "answer": ["B"]}
{"id": 1614, "answer": ["C"]}
{"id": 1612, "answer": ["A", "B", "D"]}
{"id": 1608, "answer": ["A", "C", "D"]}
{"id": 1613, "answer": ["B"]}
{"id": 1617, "answer": ["B"]}
{"id": 1620, "answer": ["C"]}
{"id": 1616, "answer": ["B", "D"]}
{"id": 1619, "answer": "保险资金投资基础资产为非标准化债权资产的集合资金信托时，其信用评级不得低于国内信用评级机构评定的AA级或相当于AA级的信用级别。"}
{"id": 1621, "answer": ["C"]}
{"id": 1623, "answer": ["C"]}
{"id": 1622, "answer": ["A", "B", "D"]}
{"id": 1625, "answer": ["B"]}
{"id": 1615, "answer": "后续合规处置方案的关键要素包括：1. 延长还款期限至2021年3月底（依据段落1、3）；2. 合规办理展期或续贷（依据段落2、4）；3. 根据实际情况追加贷款（单户不超过10万元，5万元以上部分不贴息，依据段落4）；4. 落实风险补偿金和财政贴息政策（依据段落1、5）；5. 建立资金监管和跟踪监督机制，定期监测借款人经营状况（依据段落2）。"}
{"id": 1584, "answer": ["B", "D"]}
{"id": 1627, "answer": ["C"]}
{"id": 1624, "answer": ["B"]}
{"id": 1618, "answer": ["A", "B", "C"]}
{"id": 1626, "answer": ["D"]}
{"id": 1630, "answer": ["B", "D"]}
{"id": 1632, "answer": ["B"]}
{"id": 1629, "answer": "人民银行鉴定完成后，将《中国人民银行特殊残缺污损人民币鉴定书》（一联）及密封的专用袋通过内部交换传递给受理机构。金融机构需核对专用袋、鉴定书及持有人出示的鉴定书要素是否一致，确认无误后凭鉴定结论填制《兑换单》办理兑换，并收回持有人持有的鉴定书。专用袋及封签具有不可恢复性，确保材料交接安全合规。"}
{"id": 1634, "answer": ["C"]}
{"id": 1639, "answer": ["B"]}
{"id": 1633, "answer": ["B"]}
{"id": 1628, "answer": []}
{"id": 1641, "answer": ["B"]}
{"id": 1636, "answer": ["C"]}
{"id": 1631, "answer": ["B", "C"]}
{"id": 1640, "answer": ["B", "D"]}
{"id": 1637, "answer": "调整后的人民币汇率形成机制强调的基本原则包括：以市场供求为基础，参考篮子货币汇率变动，保持人民币汇率在合理、均衡水平上的基本稳定，进一步发挥市场在汇率形成中的作用，增强双向浮动弹性。这些原则体现了市场化改革方向与稳定目标的结合。"}
{"id": 1638, "answer": "申领新版储蓄卡需完成以下安全验证：1）采用多因素身份认证，如数字证书或动态令牌设备，并结合交易密码；2）至少使用两种不同通信渠道（如短信、语音）进行动态验证码验证；3）核对持卡人身份证号、手机号等信息与银行留存信息的一致性；4）签订授权协议并完成身份验证。"}
{"id": 1642, "answer": ["C"]}
{"id": 1635, "answer": ["C"]}
{"id": 1648, "answer": ["C"]}
{"id": 1643, "answer": ["C"]}
{"id": 1650, "answer": ["B", "C"]}
{"id": 1644, "answer": ["C"]}
{"id": 1646, "answer": ["A", "B"]}
{"id": 1649, "answer": ["C"]}
{"id": 1645, "answer": ["D"]}
{"id": 1647, "answer": ["C"]}
{"id": 1652, "answer": "保险机构投资单一资产管理计划时，管理人需满足以下硬性指标：1. 公司治理、内控机制、风险管理及审计体系健全，具备国家金融管理部门认可的资产管理业务资质；2. 具备稳定的过往投资业绩，配备15名以上专业人员（其中3年以上投资经验者不少于10名，5年以上投资经验者不少于5名）；3. 证券资产管理公司上一会计年度末经审计的净资产不低于10亿元人民币。"}
{"id": 1658, "answer": ["A", "C"]}
{"id": 1656, "answer": ["A", "B", "D"]}
{"id": 1662, "answer": ["B"]}
{"id": 1655, "answer": ["B", "D"]}
{"id": 1659, "answer": ["C"]}
{"id": 1664, "answer": ["B", "D"]}
{"id": 1653, "answer": ["D"]}
{"id": 1660, "answer": ["A", "C", "D"]}
{"id": 1654, "answer": ["A", "C"]}
{"id": 1651, "answer": ["A", "C"]}
{"id": 1661, "answer": "保险机构在持有资本补充债券期间若偿付能力充足率跌破120%的警戒线，应根据段落1和段落4的要求，及时调整投资策略，采取有效措施控制相关风险，例如优化资产配置、加强风险监控或减少高风险资产持有比例，以确保偿付能力回归合规水平。"}
{"id": 1666, "answer": "银行分支机构搬迁后，需重新取得存取现金资格，应向所在地人民银行分支机构提交重新申请，具体包括：1. 提交开办存取现金业务申请书；2. 提供人民银行分支机构营业部门开户申请书回执原件及复印件；3. 提交现金管理内部控制制度和业务操作规程；4. 办理人员变更手续（如人员变动需在5个工作日内提交资料）；5. 按照人民银行要求提交其他必要文件。搬迁后需重新履行申请程序并完成相关手续。"}
{"id": 1663, "answer": "代理支库业务需配置以下会计科目：  \n1. **“代理支库存款”一级科目下的二级科目**：  \n   - **县级以上地方财政库款**：核算县级及县级以上财政预算收入和预算支出等款项，为负债类科目，库款增加时贷记，减少时借记。  \n   - **县级以上财政预算专项存款**：核算专项预算资金的收纳与支拨。  \n   - **县级以上财政预算外存款**：核算预算外资金的收纳与支拨。  \n2. **“待结算财政款项”一级科目下的二级科目**：  \n   - **代理支库待结算财政款项**：核算待报解的预算收入款项，如收纳、划分、报解等过程中的资金。  \n3. **表外科目**：  \n   - **待转国库存款利息**：核算国库存款利息的转帐。  \n以上科目分别用于核算代理支库业务中财政资金的收支、待结算款项及利息管理。"}
{"id": 1665, "answer": ["C"]}
{"id": 1668, "answer": ["B"]}
{"id": 1667, "answer": ["C"]}
{"id": 1669, "answer": ["B"]}
{"id": 1670, "answer": ["B"]}
{"id": 1672, "answer": ["D"]}
{"id": 1657, "answer": ["B", "D"]}
{"id": 1676, "answer": ["A", "B", "D"]}
{"id": 1671, "answer": ["A", "B", "C", "D"]}
{"id": 1673, "answer": ["C"]}
{"id": 1678, "answer": ["B"]}
{"id": 1679, "answer": ["B"]}
{"id": 1681, "answer": ["A", "C"]}
{"id": 1674, "answer": ["A"]}
{"id": 1680, "answer": ["B"]}
{"id": 1677, "answer": "银行需履行以下法定义务：（1）按期兑付同业存单本息（段落1第十三条）；（2）及时披露评级下调等重大事件（段落1第十七条、段落4第十七条）；（3）遵守信息披露规则，包括发行计划及发行要素公告（段落1第十四条、第十六条）；（4）接受中国人民银行的监督管理（段落2第十九条）。若评级下调导致监管评级不满足要求，可能需限制新增业务（参考段落3逻辑）。"}
{"id": 1685, "answer": ["A"]}
{"id": 1686, "answer": ["B"]}
{"id": 1683, "answer": ["A", "B", "C", "D"]}
{"id": 1687, "answer": "完整的支付结算执法检查流程应涵盖以下关键环节：1. **检查计划制定**（统筹安排检查范围和频率，避免重复检查）；2. **检查对象确定**（依据监管职责和法规确定被检查机构）；3. **现场检查实施**（进入被检查人现场监督执行支付体系管理规定）；4. **协作与配合**（被检查人需配合检查工作，必要时协调其他机构协助）；5. **检查结果处理**（撰写报告，提出违法违规行为的处理意见）；6. **规范与监督**（遵循针对性、科学性原则，并落实纪律责任追究）。"}
{"id": 1684, "answer": "银行应通过以下步骤评估集团下属企业间互保贷款风险：（1）优先考察企业第一还款来源的真实性、现金流稳定性及经营规模，避免过度依赖担保；（2）严格审核担保人资质，限制担保客户数量和单户贷款额度，防止担保链条过长；（3）开展专项排查，评估担保圈风险，对高风险客户制定针对性处置预案；（4）控制互保贷款比重，防范多头授信和连环担保风险，确保担保额度不超过企业净资产。"}
{"id": 1692, "answer": ["B"]}
{"id": 1688, "answer": ["C"]}
{"id": 1691, "answer": "清算基金与保证金的法定归属关系为：属于提交方（如信托公司、农村信用社或市场参与者）所有。使用限制包括：仅用于履行清算义务（如结算、违约处理）且不得挪作他用，需专户管理并隔离自有资产，超额部分需清退或调整。"}
{"id": 1689, "answer": "相关部门应按照《国库资金经收支付服务管理办法（试行）》要求，由商业银行或清算机构对非银行支付机构的信息采集范围进行过滤和合规审核，确保其符合规定。若发现擅自扩大信息采集范围的行为，应立即上报监管部门（如银监会），并依据监管权限提出处置意见，经批准后实施整改或处罚措施。同时，非银行支付机构需依法告知信息使用范围，不得违规使用或泄露信息。"}
{"id": 1698, "answer": ["C"]}
{"id": 1693, "answer": ["C"]}
{"id": 1696, "answer": "银行会将一年内无交易记录的单位账户视为久悬账户，根据账户要素缺失情况分类处理：重要要素缺失的账户暂不纳入系统管理并报送人民银行；其他要素缺失的账户需纳入系统管理。同时，银行不得为该单位开立或变更其他账户。若账户欠有贷款，可能进一步纳入监管并公告催办。"}
{"id": 1682, "answer": ["A", "C"]}
{"id": 1694, "answer": "科技部门推荐贷款项目时应优先推荐属于国家科技计划和专项的项目。"}
{"id": 1690, "answer": ["A", "B", "C"]}
{"id": 1697, "answer": "境外银行类合格投资者可通过以下三种渠道开展外汇衍生产品交易：（1）作为客户与托管人、结算代理人或境内其他金融机构直接交易；（2）申请成为中国外汇交易中心会员直接进入银行间外汇市场交易；（3）申请成为外汇交易中心会员通过主经纪业务进入银行间外汇市场交易。"}
{"id": 1695, "answer": ["B", "C"]}
{"id": 1701, "answer": ["D"]}
{"id": 1699, "answer": ["C"]}
{"id": 1704, "answer": ["D"]}
{"id": 1708, "answer": ["B"]}
{"id": 1709, "answer": ["A", "B"]}
{"id": 1706, "answer": ["C"]}
{"id": 1700, "answer": ["C"]}
{"id": 1702, "answer": "当特约商户出现交易量激增时，应采取以下应急措施：（1）通过交易监控系统实时监测异常交易，及时调查处理（段落2）；（2）调整动态营业额上限，必要时暂停交易或延迟清算以控制风险（段落3）；（3）启动突发事件应急预案，确保系统安全运行（段落1）；（4）对违规商户纳入黑名单，采取暂停交易、终止合作等惩戒措施（段落4）；（5）加强现场核查，核实商户信息真实性（段落5）。"}
{"id": 1703, "answer": "跨国集团通过境内外回购市场利用利率差异或汇率差异进行套利，例如将资金调往利率较高的市场进行债券回购交易，赚取利差。具体操作中，正回购融资余额受所持债券余额的100%限制，且回购资金可跨境调用（依据段落1）。"}
{"id": 1707, "answer": ["B"]}
{"id": 1712, "answer": ["B", "D"]}
{"id": 1713, "answer": ["A", "D"]}
{"id": 1714, "answer": ["B"]}
{"id": 1715, "answer": ["B"]}
{"id": 1710, "answer": "跨境绿色债券需同时满足中欧信息披露要求，特殊注意事项包括：（1）双重标准合规，同步执行中欧评估认证频率与内容；（2）确保披露信息一致性，避免因标准差异导致整改冲突；（3）通过中欧认可的第三方机构进行双重认证；（4）选择双方认可的披露平台，保障技术合规性；（5）对特殊条款（如回售选择权）需明确适用法律，优先遵循具体市场规定。"}
{"id": 1717, "answer": ["B"]}
{"id": 1716, "answer": ["A", "B"]}
{"id": 1718, "answer": ["A"]}
{"id": 1720, "answer": "支付结算检查时需保密的敏感信息包括银行卡磁道或芯片信息、卡片验证码、卡片有效期、银行卡密码、网络支付交易密码等。"}
{"id": 1675, "answer": ["A", "B", "C", "D"]}
{"id": 1719, "answer": ["A", "C"]}
{"id": 1705, "answer": ["A", "B"]}
{"id": 1722, "answer": ["A", "B"]}
{"id": 1721, "answer": "根据不同的经营许可证类型，申请延续所需提前的时间不同。对于融资性担保机构，需提前90日提交延续申请（段落2）；对于保险经纪公司，需在许可证有效期届满30日前申请延续（段落5）。若题目未明确具体类型，需依据许可证种类分别适用相应规定。"}
{"id": 1724, "answer": ["C"]}
{"id": 1725, "answer": ["A", "B", "C", "D"]}
{"id": 1728, "answer": "监管部门提出的“一行一策”整改原则是指根据商业银行的风险水平、业务特点及合规状况，制定差异化的监管措施和整改要求，针对不同银行的具体情况采取灵活的监管策略，同时结合“平稳过渡”原则，确保整改计划有序稳妥落实，避免对市场和消费者造成冲击。"}
{"id": 1730, "answer": ["C"]}
{"id": 1723, "answer": ["B"]}
{"id": 1733, "answer": ["D"]}
{"id": 1734, "answer": ["C"]}
{"id": 1726, "answer": "开通个人养老金资金账户需满足以下基本条件：1. 选择开办个人养老金业务的商业银行开立或指定资金账户（段落2第十七条）；2. 账户具有唯一性，只能选择一家符合条件的商业银行（段落2第十八条）；3. 账户性质为特殊专用账户，参照Ⅱ类户管理，并在达到国家规定领取条件前封闭运行（段落4第四条）。"}
{"id": 1729, "answer": ["A", "C", "D"]}
{"id": 1732, "answer": "持续经营触发事件是指商业银行核心一级资本充足率降至5.125%或以下时触发的事件，此时需通过减记或转股等方式恢复资本充足率至触发点以上。该事件与“无法生存触发事件”共同构成资本工具的损失吸收机制，且会计分类为负债的其他一级资本工具需同时设定二者。"}
{"id": 1735, "answer": ["C"]}
{"id": 1738, "answer": ["B"]}
{"id": 1727, "answer": "当企业因经营亏损导致净资产跌破准入标准时，投资者需关注债券价值是否明显贬损（如公开市场价格低于面值）。若符合段落1定义的“价值明显贬损”，可能触发债券条款中的减记或转股机制（如段落4），或要求企业披露亏损影响（段落2-3）。投资者应依据债券合同约定及监管披露信息，评估是否继续持有或处置债券，同时关注可能的资本工具调整（如减记）或偿债能力变化。"}
{"id": 1741, "answer": ["C"]}
{"id": 1739, "answer": ["A", "B", "C", "D"]}
{"id": 1740, "answer": ["A", "B"]}
{"id": 1742, "answer": ["C"]}
{"id": 1731, "answer": ["C"]}
{"id": 1736, "answer": "发现客户频繁反向操作导致穿仓时，应采取以下应急措施：1. **阻断异常交易**，立即暂停相关账户或交易权限（依据段落3）；2. **联系客户核实交易真实性**，确认操作意图并防范欺诈（依据段落3）；3. **加强风险监控**，调整风险控制参数，如提高保证金比例或限制交易频率（结合段落1的预防原则与段落4的频繁交易审查）；4. **向监管机构报告**，按压力测试要求披露潜在风险及改进措施（依据段落2）；5. **冻结账户或延迟结算**，防止进一步损失（参考段落3对可疑交易的处理）。需注意，具体措施应结合机构内部风控规则及监管要求执行。"}
{"id": 1745, "answer": ["B"]}
{"id": 1747, "answer": ["A", "C"]}
{"id": 1748, "answer": ["B", "D"]}
{"id": 1746, "answer": ["B", "D"]}
{"id": 1744, "answer": "群众对银行收缴的钞票有疑问时，可持《假币收缴凭证》在3个工作日内向当地鉴定单位申请鉴定（段落1第二十一条）。鉴定单位需在2个工作日内通知收缴单位报送货币，收缴单位需在2日内送达（段落4第二十三条），鉴定结果将决定是否退还真币或没收假币。若对收缴行为有异议，可向直接监管该金融机构的中国人民银行分支机构申请行政复议，或依法提起行政诉讼（段落1第二十条）。"}
{"id": 1737, "answer": ["A", "D"]}
{"id": 1749, "answer": ["C"]}
{"id": 1751, "answer": ["B"]}
{"id": 1743, "answer": ["A", "C", "D"]}
{"id": 1753, "answer": ["C"]}
{"id": 1750, "answer": "金融机构应通过以下措施确保内外对账的真实性：（1）严格实行岗位分离，记账与对账职责分开，杜绝由记账员直接对账；（2）实施“双线核对”，同时核对账户余额和发生额，确保内外账务一致性；（3）推广电子自动对账或后台集中对账，实现对账与核算岗位分离；（4）加强重点账户（如大额、异地、新开户）的实地对账，必要时上门核实；（5）将对账频率、回收率及准确性纳入考核，确保时效性；（6）完善电子对账系统安全运行机制，包括数据备份、网络隔离、病毒防护等技术措施（依据段落1、2、3、4、5）。"}
{"id": 1754, "answer": ["C", "D"]}
{"id": 1755, "answer": ["D"]}
{"id": 1757, "answer": ["A"]}
{"id": 1752, "answer": ["A", "B", "C", "D"]}
{"id": 1759, "answer": ["C"]}
{"id": 1758, "answer": ["B", "C", "D"]}
{"id": 1761, "answer": ["A", "C"]}
{"id": 1760, "answer": "当质押券市值大幅缩水时，应立即重新估值并补充担保（依据段落3第三十八条），加强价格监控，若触及警戒线需采取防控措施，触及强制平仓条件则按合同平仓（段落3第三十九条）。同时，需评估风险缓释有效性，必要时调整质押额度或采取其他风险缓释措施（段落4）。"}
{"id": 1756, "answer": ["B", "C"]}
{"id": 1764, "answer": ["B"]}
{"id": 1770, "answer": ["B"]}
{"id": 1763, "answer": "相关方应立即启动技术应急预案排除故障，优先保障外币清算处理中心运行；故障发生后1小时内向中国人民银行总行报告重大故障，同时通知相关用户并协调外部技术支持；尽快恢复业务数据和系统运行，记录故障详情并提交书面报告；若重大故障无法在可容忍时间内解决，中国人民银行可宣布暂停系统运行。"}
{"id": 1711, "answer": ["B"]}
{"id": 1768, "answer": "企业更换法人后需在“合理期限内”完成账户信息变更，通常理解为10个工作日（依据段落5）。逾期未办理且无合理理由的，银行有权采取措施适当控制账户交易（依据段落2）。具体时限可能因政策调整或银行要求略有差异，建议以最新监管规定为准。"}
{"id": 1767, "answer": "某信用社以高额贴息吸引储户可能构成违规，若违反利率管理规定或被认定为非法集资，可能面临行政处罚（如罚款、停业整顿）或刑事责任。具体处罚需依据《商业银行法》《银保监会行政处罚办法》等法规确定。"}
{"id": 1766, "answer": "债券质押品管理机构需满足以下基础运营条件：（1）为商业银行法人机构，分支机构办理业务需法人授权；（2）在中央结算公司开立甲类或乙类债券账户；（3）近三年在银行间市场无不良记录；（4）建立完善的押品管理治理架构，明确董事会、高级管理层及相关部门职责；（5）具备质押品管理的系统操作能力，包括质押品调增、调减及置换处理流程；（6）质押品范围限于国债、央行票据等符合要求的债券。"}
{"id": 1772, "answer": ["C"]}
{"id": 1771, "answer": ["A", "C"]}
{"id": 1762, "answer": []}
{"id": 1769, "answer": "异地法人金融机构首次参与外汇风险准备金计划的全流程操作要点如下：1. **提交申报**：向所在地中国人民银行省会（首府）城市中心支行提交“外汇风险准备金交存申报表”（段落1）；2. **审查与划款**：经所在地分支机构审查合格并加盖公章后，向中国人民银行上海总部办理划款手续，同时将申报表传真至上海总部（段落1、3）；3. **折算计算**：按美元计算准备金，非美元币种按国家外汇管理局公布的折算率折算为美元（段落1）；4. **专用账户管理**：上海总部设立专用账户存放准备金，负责日常管理（段落3）；5. **冻结期**：交存的准备金冻结期为1年，到期后可申请退还（段落5）。"}
{"id": 1775, "answer": ["B"]}
{"id": 1774, "answer": ["B"]}
{"id": 1778, "answer": ["A", "C", "D"]}
{"id": 1781, "answer": ["B"]}
{"id": 1773, "answer": "公司债券发行人选择银行间市场发行的两大优势是：一是利用现有基础设施（如债券发行系统）提高发行效率并降低发行成本；二是通过做市商机制和多样化的交易品种（如衍生产品交易）提升债券流动性，增强市场吸引力。"}
{"id": 1777, "answer": ["A"]}
{"id": 1779, "answer": "境外机构计划停止在中国的外币清算服务，需履行以下法定程序：1. 至少提前30日向中国人民银行和中国银行业监督管理委员会提交书面报告；2. 提交终止业务的评估报告、与入网机构达成的业务终止处置方案、终止业务的应急预案、涉及持卡人和商户权益保护的处理措施；3. 提交其他需专门说明的事项及申请材料真实性声明。同时需遵守《银行卡清算机构管理办法》中关于反洗钱、风险防范等附加要求。"}
{"id": 1783, "answer": ["B"]}
{"id": 1776, "answer": ["C"]}
{"id": 1780, "answer": ["B"]}
{"id": 1787, "answer": ["C"]}
{"id": 1785, "answer": ["B"]}
{"id": 1782, "answer": ["B"]}
{"id": 1788, "answer": ["B"]}
{"id": 1784, "answer": "以他人存单质押时需特别注意以下风控措施：1. 严格审查存单的真实性、合法性与有效性，确保无所有权争议、未被担保、未挂失、未失效或被依法止付（依据段落1、2）；2. 妥善保管质押存单，存单丢失或毁损时需立即通知出质人并共同挂失补办（依据段落3）；3. 在质押合同中明确质权实现方式、保管责任及违约责任，确保质权可有效行使（依据段落5）；4. 确保存单金额覆盖贷款本息，且贷款期限不超过存单到期日（依据段落1、4）。"}
{"id": 1790, "answer": ["C"]}
{"id": 1792, "answer": ["C"]}
{"id": 1786, "answer": "商业银行通过分支机构拓展同业客户资源需遵循以下合法操作方式：1. 由同业业务专营部门对不可电子化交易的同业业务进行委托，分支机构可代理市场营销、客户关系维护等操作性事项；2. 专营部门需对交易对手、金额、期限、定价、合同进行逐笔审批，并承担全权风险责任；3. 法人总部须对同业业务实行集中统一授权、授信及交易对手准入管理，分支机构不得超授权或转授权。此操作需符合《中国银监会办公厅关于规范商业银行同业业务治理的通知》（银监办发2014140号）相关规定。"}
{"id": 1793, "answer": []}
{"id": 1794, "answer": ["D"]}
{"id": 1791, "answer": ["C"]}
{"id": 1789, "answer": ["A", "B", "C", "D"]}
{"id": 1797, "answer": ["A"]}
{"id": 1795, "answer": ["A", "D"]}
{"id": 1799, "answer": ["D"]}
{"id": 1796, "answer": "全国性商业银行在服务重大项目上的独特优势包括：1. **广泛的网络渠道和业务协同能力**，能够覆盖更广区域并整合多种金融产品；2. **强大的金融科技支持**，提升服务效率与风险管理能力；3. **综合金融服务能力**，可为重大项目提供长期、稳定、低成本的资金支持；4. **国家战略对接能力**，通过资源调配和政策支持助力重大工程落地。这些优势使其在服务大型项目时更具规模化和系统化能力。"}
{"id": 1798, "answer": ["B"]}
{"id": 1801, "answer": ["B", "D"]}
{"id": 1800, "answer": "申报科技型中小企业资质需满足以下基本条件：（1）符合中小企业国家标准；（2）企业产品（服务）属于《国家重点支持的高新技术领域》范围，具体包括电子信息技术、生物与新医药技术、航空航天技术、新材料技术等领域。"}
{"id": 1805, "answer": ["C"]}
{"id": 1802, "answer": "工作人员应首先通过培训识别可疑交易特征（如段落3提到的多账户开户、异常交易），及时劝阻老年人汇款并联系公安机关冻结资金（段落1、段落5），同时向老年人普及防诈知识（段落2、段落4），必要时联系家属核实情况，确保资金安全并协助案件侦办。"}
{"id": 1806, "answer": ["B", "C"]}
{"id": 1808, "answer": ["B", "D"]}
{"id": 1811, "answer": "采用集中保管保证金时，操作流程需经过以下必要环节：1）由全国银行间同业拆借中心或中央国债登记结算有限责任公司在中国人民银行当地分行开立专户；2）将保证金存入该专户；3）人民银行对集中保管的保证金不计付利息。具体流程需依据段落1所述内容执行。"}
{"id": 1809, "answer": "境外机构回购违约后的处置优先级应优先动用风险准备资源（根据段落3），并依据资产的优先级（如优先债、次级债等）进行处置（根据段落5）。质押物可能作为优先处置对象以覆盖损失（根据段落1）。"}
{"id": 1810, "answer": ["C"]}
{"id": 1812, "answer": ["B"]}
{"id": 1803, "answer": []}
{"id": 1815, "answer": ["C"]}
{"id": 1813, "answer": ["C"]}
{"id": 1817, "answer": ["A"]}
{"id": 1816, "answer": ["C"]}
{"id": 1765, "answer": ["A", "B"]}
{"id": 1814, "answer": "监管机构应依据段落3要求，要求企业开展内部风险排查，由上级案防部门直接组织深入检查，确保排查独立性；同时结合段落2的监管评级结果，对存在重大缺陷的企业采取分类监管措施（如加强账户审核、限期整改）；若发现违规行为，依据段落1对监管不力情形采取相应处罚措施，确保账户开设合规性。"}
{"id": 1823, "answer": "《人民币利率互换集中清算协议》"}
{"id": 1822, "answer": ["C"]}
{"id": 1819, "answer": ["B", "C"]}
{"id": 1824, "answer": ["A", "B", "C", "D"]}
{"id": 1825, "answer": ["B"]}
{"id": 1821, "answer": "商业养老保险可通过以下形式帮助规划退休生活：1. 商业养老年金保险（含长期或终身领取功能）；2. 专属商业养老保险；3. 其他年金保险及两全保险（如生存年金、满期给付）；4. 商业养老金产品（如试点业务）；5. 养老基金管理服务。这些形式结合长期积累、风险保障和灵活领取需求，支持退休资金规划。"}
{"id": 1818, "answer": ["A"]}
{"id": 1807, "answer": ["B"]}
{"id": 1827, "answer": ["B"]}
{"id": 1830, "answer": ["B"]}
{"id": 1831, "answer": ["A", "C"]}
{"id": 1826, "answer": "银行业在为PPP项目提供融资时需规避的违规操作包括：1. 违规为地方政府提供债务融资，导致隐性债务风险（段落2、段落3、段落4）；2. 资金未按项目用途使用，如挪用至房地产或其他禁止领域（段落2、段落3、段落4）；3. 未严格审查项目合规性，未取得投资、环保、土地等审批手续（段落1）；4. 贷款发放未与项目进度及资本金到位情况匹配，导致资金滞留或闲置（段落2、段落4）；5. 贷款三查（贷前调查、贷中审查、贷后检查）未严格执行，导致风险失控（段落3、段落4）。"}
{"id": 1829, "answer": ["D"]}
{"id": 1828, "answer": ["A", "D"]}
{"id": 1832, "answer": ["A", "C"]}
{"id": 1836, "answer": ["B", "D"]}
{"id": 1834, "answer": "优先股强制转股触发的申报程序包含以下关键环节：1. 股东大会审议优先股强制转换事项（包括转换价格的确定方式）；2. 商业银行向银保监会提交审查并获决定；3. 履行《证券法》及证监会规定的临时报告、公告等信息披露义务；4. 若转换导致控制权变化，需符合证监会关于控制权变动的额外规定。"}
{"id": 1838, "answer": ["C"]}
{"id": 1839, "answer": ["B"]}
{"id": 1835, "answer": ["A"]}
{"id": 1840, "answer": ["C"]}
{"id": 1837, "answer": ["C"]}
{"id": 1833, "answer": ["A"]}
{"id": 1843, "answer": ["A", "C"]}
{"id": 1841, "answer": ["B", "D"]}
{"id": 1846, "answer": ["A"]}
{"id": 1842, "answer": ["B"]}
{"id": 1845, "answer": ["B", "D"]}
{"id": 1844, "answer": "境外央行类机构完成备案后仍被限制交易的可能原因包括：1. 未满足中国人民银行的宏观审慎管理要求，如交易行为不符合资产保值增值的合理需要；2. 未按规定委托中国人民银行或具备资质的结算代理人进行交易和结算，或未签署结算代理协议；3. 未履行账户信息报送义务，如未按时报送人民币账户余额等数据（依据段落5）。这些因素均可能导致交易权限受限。"}
{"id": 1848, "answer": ["B"]}
{"id": 1820, "answer": ["A"]}
{"id": 1849, "answer": ["A"]}
{"id": 1847, "answer": "贷款人可采取的风控手段包括：1. 要求借款人整改违规行为（段落2）；2. 提前收回贷款（段落4）；3. 调整贷款支付方式（段落4）；4. 调整贷款利率并收取罚息（段落4）；5. 压降授信额度或停止贷款发放（段落4）；6. 下调贷款风险分类（段落2）。这些措施均依据合同约定及监管要求实施。"}
{"id": 1854, "answer": ["C"]}
{"id": 1856, "answer": ["A"]}
{"id": 1852, "answer": ["B", "D"]}
{"id": 1851, "answer": ["B"]}
{"id": 1850, "answer": ["A"]}
{"id": 1853, "answer": ["A"]}
{"id": 1855, "answer": "金融租赁公司发行二级资本债券的材料准备需参考《中国银监会市场准入工作实施细则（试行）》（银监发〔2015〕47号）中商业银行发行二级资本债券的相关要求，并需符合《商业银行资本管理办法（试行）》（银监发〔2012〕56号）和《中国银监会关于商业银行资本工具创新的指导意见》（银监发〔2012〕56号）对二级资本工具的合格标准要求。"}
{"id": 1857, "answer": "商业银行使用第三方估值机构的估值结果时，需评估第三方机构的权威性、独立性及专业性，并对估值模型的数理严谨性、压力测试和敏感性分析结果进行验证，同时将模型估值与实际市场价值或独立基准模型进行比较。具体要求包括：确保第三方机构具备专业资质，模型假设合理，通过压力测试验证模型稳定性，并与市场实际数据交叉核对以降低估值偏差。"}
{"id": 1860, "answer": ["C"]}
{"id": 1861, "answer": ["B"]}
{"id": 1858, "answer": "借名贷款通常通过以下方式伪装合法：1. 化整为零，如社会人员和企业借用多个自然人名义分散取得贷款，逃避审批程序（段落1）；2. 伪造资料，如担保公司伪造客户虚假资料办理假按揭贷款（段落1）；3. 利用职务便利，如农村中小金融机构职工借用他人名义贷款（段落1）；4. 技术手段伪装，如通过统一IP地址或境外IP地址隐藏交易来源（段落2）。"}
{"id": 1859, "answer": ["D"]}
{"id": 1866, "answer": ["B"]}
{"id": 1862, "answer": ["B"]}
{"id": 1864, "answer": "军人保障卡正面印有武警部队卡面要素，包括卡名称（中国人民武装警察部队军人保障卡）、持卡人姓名、照片、警徽、一维条码、保障卡号和背景图案等；背面印有银行卡面要素（具体包含银行磁条信息及借记卡相关数据）。"}
{"id": 1865, "answer": ["B"]}
{"id": 1863, "answer": []}
{"id": 1867, "answer": ["A"]}
{"id": 1868, "answer": ["C"]}
{"id": 1870, "answer": ["B"]}
{"id": 1869, "answer": "公路建设中“路衍专营”的核心要求是独立运营和分账管理。具体包括：1. 路衍专营需作为独立实体运作，吸引社会资本参与，确保运营自主性；2. 对路衍专营收入与其他收入实行分账管理，优先用于偿还银行保险机构融资，保障资金合规使用。"}
{"id": 1873, "answer": ["A", "D"]}
{"id": 1875, "answer": ["C"]}
{"id": 1877, "answer": "7万元"}
{"id": 1876, "answer": ["C"]}
{"id": 1878, "answer": ["B"]}
{"id": 1872, "answer": "应采取以下风控措施：  \n1. **核查租赁物权属合法性**：根据段落3，确保文物拍卖标的合法取得并完成权属登记，防止虚构租赁物或权属不清问题（段落2）。  \n2. **审查关联交易合规性**：若合作方与融资租赁公司存在关联关系，需遵循独立交易原则，确保定价公允并经股东（大）会批准（段落3）。  \n3. **监控业务集中度与风险**：依据段落1，评估业务集中度及关联度是否超标，避免过度依赖单一合作方。  \n4. **报告可疑交易**：根据段落4，若发现文物交易涉及洗钱、恐怖融资等可疑行为，需及时提交可疑交易报告。  \n5. **强化尽职调查**：对合作方的交易背景、文物来源及交易目的进行深入核查，防范违法违规融资（段落2）。"}
{"id": 1880, "answer": ["B", "C"]}
{"id": 1881, "answer": ["C"]}
{"id": 1879, "answer": ["C"]}
{"id": 1874, "answer": ["B", "C"]}
{"id": 1882, "answer": ["B"]}
{"id": 1883, "answer": ["B"]}
{"id": 1885, "answer": ["B"]}
{"id": 1886, "answer": ["A"]}
{"id": 1884, "answer": ["A", "B"]}
{"id": 1888, "answer": ["B"]}
{"id": 1890, "answer": ["C"]}
{"id": 1804, "answer": []}
{"id": 1887, "answer": ["C"]}
{"id": 1897, "answer": ["B", "D"]}
{"id": 1891, "answer": "债券远期交易的定价需参考的主要市场指标包括现货债券的市场价值（段落4）、无风险利率（段落2）、久期（段落2的久期法）、信用利差（段落1的信用风险资本要求）及市场波动率（段落5的市场风险敏感性分析）。影响因素主要为利率变动（影响现值和久期）、信用风险变化（影响信用利差）、市场供需（影响现货价格）及宏观经济状况（如通胀预期）。这些因素通过资本要求计算和风险暴露评估间接体现于定价模型中。"}
{"id": 1899, "answer": ["B"]}
{"id": 1895, "answer": ["B"]}
{"id": 1871, "answer": ["A"]}
{"id": 1893, "answer": ["D"]}
{"id": 1894, "answer": ["C"]}
{"id": 1900, "answer": ["C"]}
{"id": 1896, "answer": "银行对境外投资项目授信时需特别关注以下环保风险管理要点：（1）严格遵守项目所在国家或地区的环保法律及国际良好做法（如赤道原则）；（2）对能源资源、农林牧渔等高风险行业实施重点审查，必要时征求第三方意见；（3）开展全面尽职调查，审查环境合规文件，并通过合同条款要求客户提交环境风险报告及违约救济措施；（4）按项目环境影响程度分类管理，对高风险项目（如A类）要求建设单位及第三方建立环境管理制度；（5）动态监控客户环境风险控制措施，严格限制存在重大环境违规的客户授信。"}
{"id": 1905, "answer": ["B", "D"]}
{"id": 1898, "answer": ["B"]}
{"id": 1902, "answer": ["A", "B", "D"]}
{"id": 1903, "answer": ["C"]}
{"id": 1904, "answer": "农村合作金融机构可通过提升资金运用效率（如专业化服务与集约化操作）和加强资产负债综合管理（如优化资金配置与收入结构多元化）两种途径改善资金收益。"}
{"id": 1901, "answer": "发现定期存单被盗时，应立即向存款所在银行提交书面挂失申请（特殊情况可先口头挂失但需5个工作日内补办），并持单位公函及经办人身份证件办理相关手续。同时，向公安机关报案追究盗用责任。若存单涉及质押贷款，需与贷款人协商处理，银行需妥善保管存单，因保管不善导致丢失的由贷款人承担责任。挂失生效后，若存单在挂失前已被支取，银行不承担赔偿责任。"}
{"id": 1906, "answer": ["B"]}
{"id": 1908, "answer": ["C"]}
{"id": 1910, "answer": ["C"]}
{"id": 1909, "answer": ["D"]}
{"id": 1911, "answer": ["A", "C"]}
{"id": 1914, "answer": ["B"]}
{"id": 1915, "answer": ["D"]}
{"id": 1913, "answer": ["C"]}
{"id": 1916, "answer": ["B"]}
{"id": 1907, "answer": ["A"]}
{"id": 1912, "answer": ["A", "C"]}
{"id": 1917, "answer": ["A", "B", "D"]}
{"id": 1919, "answer": ["A", "C"]}
{"id": 1918, "answer": ["B", "D"]}
{"id": 1920, "answer": ["B"]}
{"id": 1921, "answer": ["C"]}
{"id": 1922, "answer": ["B"]}
{"id": 1889, "answer": ["C"]}
{"id": 1892, "answer": ["C"]}
{"id": 1923, "answer": "城市商业银行与外国银行在华分所在参与交易所债券交易时，准入门槛无实质性差异。根据2019年《关于银行在证券交易所参与债券交易有关问题的通知》（证监发201981号），两者均被纳入参与主体范围，需满足“依法合规、风险可控、商业可持续”等共同前提条件，并遵循统一的内控管理、账户开立及结算流程。段落5关于境外机构在银行间市场的备案要求不适用于交易所交易，因此不存在针对在华外资银行的额外准入门槛。"}
{"id": 1927, "answer": ["B"]}
{"id": 1930, "answer": "清算窗口期仍然未能完成的排队业务，外币清算处理中心应予以退回，但轧差净额业务除外。"}
{"id": 1929, "answer": ["B", "D"]}
{"id": 1926, "answer": "确保条码支付交易信息的真实性与安全性需采取以下措施：  \n1. **信息完整性与真实性**：根据真实场景选用交易类型，完整发送交易信息（如商户名称、交易时间、金额等），并通过特定域标识交易类型，确保信息可追溯（段落2第二十条）。  \n2. **技术防护**：采用安全单元（SE）、支付标记化、加密传输、数字签名等技术手段，防止交易信息被篡改或隐匿（段落1、段落3）。  \n3. **敏感信息管控**：条码仅包含当次支付必要信息，禁止泄露客户账户信息，支付指令需经客户确认或授权发起（段落4、段落5）。  \n4. **风险监控**：结合大数据分析和用户行为建模，建立风险监测与预警机制，强化交易安全（段落1）。"}
{"id": 1933, "answer": "社团贷款的核心原则是“自愿协商、权责明晰、讲求效益、利益共享、风险共担”。"}
{"id": 1928, "answer": "营业终了前柜员尾箱的操作标准流程包括：清点尾箱现金并核对账款，记录现金收付日记簿和库存现金登记簿，确保日清日结；将钱、章、凭证入箱上锁；验款入库；尾箱内物品全部入库并核对账实相符，保证账款一致。同时需严格遵守安全交接与监控要求，确保全程无缝交接和账实相符。"}
{"id": 1932, "answer": ["B"]}
{"id": 1931, "answer": "区分金融机构清算交收账户与自有资金账户的关键在于：  \n1. **账户性质**：清算交收账户专用于证券交易结算、托管资金、客户备付金等特定业务（如证券公司客户交易结算资金账户、资管产品托管资金账户等），而自有资金账户为金融机构自身运营资金账户。  \n2. **管理要求**：清算交收账户需在系统中特殊标识，并在冻结扣划时受到法律保护（如不得整体冻结或超出涉案金额范围），而自有资金账户无此类限制。  \n3. **资金用途**：清算交收账户资金具有特定业务规则（如保证金、清算基金等），而自有资金账户用于日常运营或投资。  \n4. **法律依据**：银行业金融机构需通过核实账户资金性质、系统标识及冻结扣划提示等措施进行区分（见段落1、2、4、5）。"}
{"id": 1925, "answer": ["B"]}
{"id": 1935, "answer": ["A"]}
{"id": 1937, "answer": "国库资金经收支付服务的两种业务模式区别主要体现在网络通道连接路径和合作协议签署方。模式一中，非银行支付机构通过清算机构与商业银行连接，依托商业银行直连国库的通道，并需三方（支付机构、商业银行、清算机构）签订协议；模式二中，非银行支付机构直接依托清算机构直连国库的通道，仅需支付机构与清算机构签订协议。"}
{"id": 1934, "answer": "根据现有检索内容，未明确提及县级农信社改制时法人股的具体最低比例要求，仅说明对经济欠发达地区可酌情降低比例。通常情况下，法人股比例需达到监管规定的标准（如20%或更高），但需结合具体政策文件进一步确认。"}
{"id": 1936, "answer": "投保人年龄超过65岁时，销售保单需注意以下特殊流程：1. 核保时严格复核产品适合性、投保信息及签名，发现不适合或信息不实不得承保（段落1）；2. 销售分红型、万能型等产品需投保人确认已阅读条款并签字，保险公司需提供保单状态报告等信息查询路径（段落2）；3. 加强投保告知义务，确保投保人了解产品功能、违约后果等，并签署相关文件（段落3）；4. 互联网销售需完整记录操作轨迹，确保可回溯管理（段落4）；5. 提供适老化服务，如便捷投保通道和符合老年人特点的披露方式（段落5）。"}
{"id": 1938, "answer": ["A", "B", "D"]}
{"id": 1942, "answer": ["B"]}
{"id": 1939, "answer": []}
{"id": 1940, "answer": ["A", "B", "D"]}
{"id": 1944, "answer": ["B", "D"]}
{"id": 1941, "answer": "保险资产管理公司监管评级的基本流程包括：1. 公司自评估（每年5月底前提交经法定代表人签署的自评估结果及证明材料）；2. 银保监会复核评价（依据日常监管数据及评分标准进行）；3. 反馈评级结果（以书面形式通知公司并通报存在问题）；4. 档案归集（完成评级信息及工作底稿归档）。同时，银保监会将根据评级结果实施差异化监管措施。"}
{"id": 1945, "answer": ["B", "C"]}
{"id": 1943, "answer": "需满足以下条件：1. 集团注册资本金按境内所有成员汇总计算；2. 由集团一级法人或其授权机构统一申请银行间即期外汇市场会员资格；3. 建立集团内部外汇资金集中管理制度；4. 提供外汇管理合规证明、内部交易管理制度及财务报告等申请材料。"}
{"id": 1947, "answer": "备案审核中发现材料矛盾时，备案主体应及时向主管部门反馈，主管部门可依法核实并要求补充材料；若拒不改正，可处以5万元以下罚款。"}
{"id": 1948, "answer": "地方银行的分支机构数据拆分和报送责任由地方性法人银行承担，需按附表格式、时间要求向属地监管部门报送，并确保数据准确性与合理性。具体要求包括通过正式发文报送、校验数据准确性及合理性和按监管机构指定的机构类型填报。"}
{"id": 1951, "answer": "全国银行间同业拆借中心和中央国债登记结算有限责任公司。"}
{"id": 1955, "answer": ["C"]}
{"id": 1953, "answer": ["B"]}
{"id": 1950, "answer": "新版政策在资本补充债券投资准入方面的关键性放宽包括：取消发行人总资产和净资产门槛，将资本充足率要求调整为“符合监管规定”并取消外部信用等级AAA级要求；取消二级资本债券（AAA级）和无固定期限资本债券（AA+级）的债项评级要求，从而降低投资门槛并扩大可投资范围。"}
{"id": 1949, "answer": ["B"]}
{"id": 1954, "answer": ["B"]}
{"id": 1946, "answer": []}
{"id": 1956, "answer": "境内个人参与境外上市公司员工持股计划的购付汇流程需通过境内公司选定的境内代理机构统一办理，具体包括：1）开立境内专用外汇账户；2）办理外汇登记及资金划转；3）由境内代理机构按规定进行国际收支统计间接申报。相关材料需提供具有法律效力的中文文本，且需遵守国家外汇管理局的监督与管理要求。"}
{"id": 1957, "answer": ["B"]}
{"id": 1960, "answer": ["D"]}
{"id": 1924, "answer": ["B"]}
{"id": 1962, "answer": "1. **强化客户确认机制**：系统应集成语音自助提示、屏幕显示等功能，实时向客户展示业务性质和金额，并要求客户确认（依据段落1）。  \n2. **完善授权与复核流程**：对大额交易实行远程复核（授权）与现场审核结合的双人复核机制，确保操作合规（依据段落1）。  \n3. **部署实时监控与预警系统**：通过交易流水追踪、异常行为分析等功能，及时发现空存实取等可疑操作（依据段落2和段落5）。"}
{"id": 1958, "answer": "跨境债券违约案件中，协调境内外司法管辖权和法律适用需依托统一的法律框架和执法机制。根据《公司信用类债券信息披露管理办法》（段落3、5），中国通过统一信息披露责任、建立市场化违约处置机制及跨市场执法合作，减少法律冲突。同时，清算机构间的风险准备资源和违约处置安排（段落2）可作为违约后的协调工具。尽管具体管辖权选择未明确，但统一执法和信息披露标准为协调提供了基础，可能优先适用中国法律或通过国际条约解决争议。"}
{"id": 1959, "answer": "通过电子渠道开立Ⅲ类户需完成以下步骤：1. 绑定本人同名Ⅰ类户；2. 采用数字证书或电子签名等安全验证方式；3. 从同名Ⅰ类户向Ⅲ类户转入任意金额以激活账户；4. 确认账户余额不超过1000元，激活后剩余资金原路返回Ⅰ类户。若身份信息未变化，开立时无需重复填写身份信息或出示身份证件。"}
{"id": 1963, "answer": "继承人需具备第一顺序继承人身份，并提供合法有效的身份证明、死亡证明及继承关系证明文件，同时需基于合法、正当利益提出查询申请，且仅可查询已故存款人生前6个月及死亡后的账户交易明细。"}
{"id": 1964, "answer": ["D"]}
{"id": 1965, "answer": ["B"]}
{"id": 1952, "answer": ["A", "B", "D"]}
{"id": 1966, "answer": "供应链金融模式下，上下游企业获取融资的关键凭证是应收账款、预付款、存货、仓单等动产质押物。"}
{"id": 1968, "answer": "境外机构投资者可通过原件邮寄或委托银行间市场结算代理人代理递交方式向中国人民银行提交中国银行间市场投资备案表。若委托结算代理人，需签署结算代理协议并按规定备案。"}
{"id": 1969, "answer": "违法行为处于连续状态的判定标准是基于同一违法故意，连续实施数个独立的违法行为并违反同一监管规定（段落1、3）。其与继续状态的本质区别在于：连续状态涉及多个独立的违法事实，而继续状态是单一违法行为的持续存在（如违法状态未终止）。例如，多次独立的违规行为构成连续状态，而未及时终止的单次违法行为则属于继续状态（段落3）。"}
{"id": 1974, "answer": "银行机构需提交的核心材料包括：批量迁移申请表、批量迁移数据文件，以及需批量迁移的核准类银行结算账户的开户许可证正本或开户许可证遗失证明（第七条第二款规定的情形除外）。若迁移后注册地、账号不发生变动，可豁免开户许可证及一致性协议要求。"}
{"id": 1978, "answer": ["D"]}
{"id": 1970, "answer": "场内衍生产品交易完成后必须载明的四项确认书要素包括交易日、交易各方名称、交易价格、交易数量及交割方式。"}
{"id": 1973, "answer": "外商投资企业发生股权转让后，需在工商变更登记或备案后15个工作日内向央行分支机构提交变更材料。所需文件包括外商投资企业批准证书复印件、营业执照副本、组织机构代码证（合伙企业除外），以及股权转让协议、董事会决议等（依据段落1和段落3）。"}
{"id": 1971, "answer": "境外清算行与普通外资银行的准入差别主要体现在监管框架、业务范围及资金来源要求上。境外清算行需符合中国人民银行关于人民币跨境结算和债券市场投资的特定规定，其人民币资金来源限于央行货币合作、跨境贸易或投资业务，并需满足真实性审核及信息报送要求（段落3、段落5）。而普通外资银行的准入需遵循《外资银行管理条例实施细则》，包括设立分行的合并考核、资产负债管理等常规监管要求（段落2）。境外清算行的准入更聚焦于人民币国际化相关业务，而普通外资银行则需符合更广泛的银行业务监管框架。"}
{"id": 1976, "answer": "户籍迁移后办理教育储蓄异地兑付手续需满足以下要求：1. 必须在存款到期后办理异地托收；2. 提供户口迁移证明及正在接受非义务教育的身份证明；3. 未能提供证明的，不享受利率优惠并需征收利息所得税。时限要求为存款到期后方可办理，具体需以存款合同约定的到期日为准。"}
{"id": 1980, "answer": ["B"]}
{"id": 1972, "answer": ["B"]}
{"id": 1977, "answer": ["C"]}
{"id": 1961, "answer": ["D"]}
{"id": 1984, "answer": ["B"]}
{"id": 1975, "answer": "依据《中华人民共和国中国人民银行法》第四十六条进行处罚。具体条款为：银行开立匿名账户、假名账户，或者与身份不明的企业进行交易的，依据该法第四十六条处罚。"}
{"id": 1979, "answer": "外资银行法人化改制后的资本金本外币转换需遵守以下程序性要求：1. 提前20日书面告知所在地外汇局分局；2. 符合《银行办理结售汇业务管理办法实施细则》（汇发〔2014〕53号）第二十五条第（一）款要求；3. 若涉及政策性注资背景，仍按原细则办理；4. 需将资本金本外币转换纳入银行结售汇统计制度（段落3）。此外，还需遵守反洗钱和反恐怖融资相关法规（段落1）。"}
{"id": 1981, "answer": "第三方支付公司与技术服务商合作时需规避的操作包括：1. 严禁将特约商户资质审核、受理协议签订、资金结算、交易处理、风险监测、主密钥管理、差错处理等核心业务交由技术服务商办理；2. 禁止技术服务商截留特约商户结算资金；3. 必须确保技术服务商的业务系统符合《非金融机构支付业务设施技术要求》；4. 禁止业务转让或转包。这些规定依据段落2和段落3中的中国人民银行相关指导意见。"}
{"id": 1983, "answer": ["B"]}
{"id": 1982, "answer": ["A", "B", "D"]}
{"id": 1967, "answer": ["B"]}
{"id": 1987, "answer": "若农村资金互助社筹建期无法按时完成，申请人应于筹建期限届满前1个月内向银监局提交筹建延期申请，银监局将在20日内决定是否批准延期，最长可延长期限为3个月。逾期未提交开业申请的，筹建许可将被注销。"}
{"id": 1985, "answer": ["B"]}
{"id": 1986, "answer": "外汇指定银行需通过审核支票是否用于自营进口贸易项下支付（段落2）、核对支票上的国际收支交易编码（段落4）、审查企业提供的有效商业单据及进口付汇核销单（段落3、段落5），并确保资金来源与贸易背景一致，从而区分资金来源。"}
{"id": 1992, "answer": ["B", "D"]}
{"id": 1995, "answer": ["C"]}
{"id": 1988, "answer": "商业银行通过以下措施平衡电话银行的便利性与安全性：1）开展风险教育，提升客户密码保护意识；2）对转账功能进行风险分类，设置差异化额度和次数限制；3）在高风险操作中增加多因素身份验证（如CVV码、身份证信息）；4）限制登录信息输入次数，防范试探性攻击；5）建立异常交易监测机制，实时预警潜在风险。这些措施在保障安全的同时，通过分层控制维持服务的便捷性。"}
{"id": 1991, "answer": ["A", "C"]}
{"id": 1990, "answer": "申请成为条码支付特约商户需满足以下基本条件：（1）依法设立并合法经营；（2）提供真实有效的营业执照及法定代表人或负责人有效身份证件；（3）无不良信息记录且不在特约商户黑名单中。"}
{"id": 1989, "answer": ["A", "C"]}
{"id": 1997, "answer": "联合授信委员会应首先评估境外借款是否导致企业实际融资接近或超过联合授信额度，或引发偿债风险（如触发段落5中的预警条件）。若触发预警，需召开联席会议，调整授信额度并制定风险管控措施（如审慎审批、风险缓释手段）。若未超5‰且风险可控，可要求相关银行报告融资信息（段落3）。最终需经成员银行表决通过重大调整，并动态更新融资台账（段落1、2、5）。"}
{"id": 1996, "answer": ["D"]}
{"id": 1998, "answer": ["B"]}
{"id": 1994, "answer": "Ⅲ类账户突然无法转账消费的合规性原因可能包括：1）超出日累计2000元或年累计5万元的出金限额；2）账户余额超过2000元的限额；3）银行因监测到可疑交易或异常行为而限制账户功能；4）未通过绑定账户验证非绑定账户入金；5）尝试超出Ⅲ类户限定范围的操作（如透支或非消费类转账）。"}
{"id": 1999, "answer": "企业首次申请黄金进出口资质需提交以下基本材料：1. 书面申请（载明企业名称、住所、概况、进出口用途及计划数量）；2. 《黄金及黄金制品进出口申请表》；3. 加盖公章的企业法人营业执照复印件；4. 《对外贸易经营者备案表》或《外商投资企业批准证书》复印件；5. 申请人近2年无违法行为的说明材料；6. 生产、加工或使用黄金制品的企业需提交近3年纳税记录、地市级环保部门出具的污染物排放许可证件及年度达标检测报告；7. 外贸企业需提交海关认证管理证明及近3年纳税记录；8. 出口黄金制品的企业需提交国内黄金原料增值税发票；9. 教育机构、科研机构需提交承担国家科研项目的证明材料。具体材料需根据企业类型调整。"}
{"id": 1993, "answer": ["A"]}
